[{"id": 3393269, "title": "Shayzar I: The Fortification of the Citadel", "created_at": "2013-04-26T05:25:01.808-07:00", "url": "https://www.academia.edu/3393269/Shayzar_I_The_Fortification_of_the_Citadel?f_ri=332912", "dom_id": "work_3393269", "summary": "This book presents the results obtained from the historical and archaeological investigations carried out in the framework of a project centred on the site of Shayzar, in Central Syria: Shayzar Project: study of the fortified settlement in Bilad al-Sham. On the basis of a detailed analysis of the archaeological evidence, and of the study of the written documentation available, the book examines the origins and the development of this fortification, especially in relation to the most crucial period as regard as the building of the citadel, i.e., the span of time that stretches from the 10th to the 13th centuries; it also discusses the development of building techniques in the context of military architecture. ", "downloadable_attachments": [{"id": 64448060, "asset_id": 3393269, "asset_type": "Work", "always_allow_download": false}], "ordered_authors": [{"id": 3950213, "first_name": "Cristina", "last_name": "Tonghini", "domain_name": "unive", "page_name": "CristinaTonghini", "display_name": "Cristina Tonghini", "profile_url": "https://unive.academia.edu/CristinaTonghini?f_ri=332912", "photo": "https://0.academia-photos.com/3950213/1480320/1805951/s65_cristina.tonghini.jpg"}], "research_interests": [{"id": 1344, "name": "Islamic Archaeology", "url": "https://www.academia.edu/Documents/in/Islamic_Archaeology?f_ri=332912", "nofollow": false}, {"id": 7468, "name": "Military Architecture", "url": "https://www.academia.edu/Documents/in/Military_Architecture?f_ri=332912", "nofollow": false}, {"id": 12887, "name": "Islamic' Architecture", "url": "https://www.academia.edu/Documents/in/Islamic_Architecture?f_ri=332912", "nofollow": false}, {"id": 61835, "name": "Urban Design", "url": "https://www.academia.edu/Documents/in/Urban_Design?f_ri=332912", "nofollow": false}, {"id": 71868, "name": "Sustainable Urban Planning", "url": "https://www.academia.edu/Documents/in/Sustainable_Urban_Planning?f_ri=332912"}, {"id": 71870, "name": "Metaphor in Architectural Design", "url": "https://www.academia.edu/Documents/in/Metaphor_in_Architectural_Design?f_ri=332912"}, {"id": 71872, "name": "Architectural Phenomenology", "url": "https://www.academia.edu/Documents/in/Architectural_Phenomenology?f_ri=332912"}, {"id": 332912, "name": "Islamic military history", "url": "https://www.academia.edu/Documents/in/Islamic_military_history?f_ri=332912"}, {"id": 1019476, "name": "The Making of Islamic Architecture", "url": "https://www.academia.edu/Documents/in/The_Making_of_Islamic_Architecture?f_ri=332912"}, {"id": 1019477, "name": "Architectural Heritage Conservation", "url": "https://www.academia.edu/Documents/in/Architectural_Heritage_Conservation?f_ri=332912"}]}, {"id": 222910, "title": "Arab Nomads and Seljuq Military", "created_at": "2010-03-23T11:08:25.480-07:00", "url": "https://www.academia.edu/222910/Arab_Nomads_and_Seljuq_Military?f_ri=332912", "dom_id": "work_222910", "summary": "During the 10th and the 12th centuries the relation between the successive military states and the Arab nomads chnaged. The strength and political organisation of the tribal groups were direct reflections of the military and economical strength of the sedentary powers. \nThe first period is characterised by a new wave of tribal immigration and their domination of the region, which is linked to the surrounding political situation. They grew in power and developed a kind of \u201edimorphic state\u201c - a Bedouin ruler who presented himself as urban but had his men in the pasture - whenever they were under special support of one of the surrounding sedentary powers. \nIn the second phase, the Saljuq period, the tribes competed in land use with the Saljuq military state. The Sal\u00a1uqs needed land in order to distribute it to the army and to develop it as iqta'. The power struggles of the various Saljuq pretenders which began in this period ended with the tribal groups being ousted or exterminated as further result. Only some amirs with tribal background survived this situation owing to their neutral political position and the possession of fortified locations. \nThe third phase witnessed the formal integration of newly arrived nomadic groups into the framework of the Zangid-Ayyubid state. Operating at a much higher economic and military level the Zangids were able to tax the nomads, while the Ayyubids were in a position to nominate the amir al-'arab, the chief of the Bedouins.\n", "downloadable_attachments": [{"id": 798738, "asset_id": 222910, "asset_type": "Work", "always_allow_download": false}], "ordered_authors": [{"id": 74197, "first_name": "Stefan", "last_name": "Heidemann", "domain_name": "uni-hamburg", "page_name": "StefanHeidemann", "display_name": "Stefan  Heidemann", "profile_url": "https://uni-hamburg.academia.edu/StefanHeidemann?f_ri=332912", "photo": "https://0.academia-photos.com/74197/20488/19005/s65_stefan.heidemann.jpg"}], "research_interests": [{"id": 137, "name": "Economic History", "url": "https://www.academia.edu/Documents/in/Economic_History?f_ri=332912", "nofollow": false}, {"id": 6693, "name": "Palestine", "url": "https://www.academia.edu/Documents/in/Palestine?f_ri=332912", "nofollow": false}, {"id": 6730, "name": "Eurasian Nomads", "url": "https://www.academia.edu/Documents/in/Eurasian_Nomads?f_ri=332912", "nofollow": false}, {"id": 7725, "name": "Urban Studies", "url": "https://www.academia.edu/Documents/in/Urban_Studies?f_ri=332912", "nofollow": false}, {"id": 15800, "name": "Islamic History", "url": "https://www.academia.edu/Documents/in/Islamic_History?f_ri=332912"}, {"id": 25118, "name": "Medieval Islamic History", "url": "https://www.academia.edu/Documents/in/Medieval_Islamic_History?f_ri=332912"}, {"id": 43809, "name": "Jerusalem", "url": "https://www.academia.edu/Documents/in/Jerusalem?f_ri=332912"}, {"id": 95298, "name": "Crusaders", "url": "https://www.academia.edu/Documents/in/Crusaders?f_ri=332912"}, {"id": 136095, "name": "Bedouins", "url": "https://www.academia.edu/Documents/in/Bedouins?f_ri=332912"}, {"id": 235116, "name": "Zengids", "url": "https://www.academia.edu/Documents/in/Zengids?f_ri=332912"}, {"id": 332912, "name": "Islamic military history", "url": "https://www.academia.edu/Documents/in/Islamic_military_history?f_ri=332912"}, {"id": 392361, "name": "Great Seljuqs", "url": "https://www.academia.edu/Documents/in/Great_Seljuqs?f_ri=332912"}, {"id": 495224, "name": "Zangids", "url": "https://www.academia.edu/Documents/in/Zangids?f_ri=332912"}, {"id": 495334, "name": "Numayrids", "url": "https://www.academia.edu/Documents/in/Numayrids?f_ri=332912"}, {"id": 560438, "name": "Islamic taxes", "url": "https://www.academia.edu/Documents/in/Islamic_taxes?f_ri=332912"}]}, {"id": 41275817, "title": "Les Mamelouks et la guerre : strat\u00e9gie, tactique et id\u00e9ologie (1250-1375), Paris Panth\u00e9on Sorbonne University/SOAS, 2019.", "created_at": "2019-12-12T06:48:51.372-08:00", "url": "https://www.academia.edu/41275817/Les_Mamelouks_et_la_guerre_strat%C3%A9gie_tactique_et_id%C3%A9ologie_1250_1375_Paris_Panth%C3%A9on_Sorbonne_University_SOAS_2019?f_ri=332912", "dom_id": "work_41275817", "summary": null, "downloadable_attachments": [{"id": 61495123, "asset_id": 41275817, "asset_type": "Work", "always_allow_download": false}], "ordered_authors": [{"id": 10670362, "first_name": "Mehdi", "last_name": "BERRIAH", "domain_name": "independent", "page_name": "mehdiBERRIAH", "display_name": "Mehdi BERRIAH", "profile_url": "https://independent.academia.edu/mehdiBERRIAH?f_ri=332912", "photo": "https://0.academia-photos.com/10670362/15596225/35752039/s65_mehdi.berriah.jpg"}], "research_interests": [{"id": 133, "name": "Military History", "url": "https://www.academia.edu/Documents/in/Military_History?f_ri=332912", "nofollow": false}, {"id": 579, "name": "Strategy (Military Science)", "url": "https://www.academia.edu/Documents/in/Strategy_Military_Science_?f_ri=332912", "nofollow": false}, {"id": 580, "name": "Tactics (Military Science)", "url": "https://www.academia.edu/Documents/in/Tactics_Military_Science_?f_ri=332912", "nofollow": false}, {"id": 6502, "name": "Mamluk Studies", "url": "https://www.academia.edu/Documents/in/Mamluk_Studies?f_ri=332912", "nofollow": false}, {"id": 16155, "name": "Mamluk History", "url": "https://www.academia.edu/Documents/in/Mamluk_History?f_ri=332912"}, {"id": 42271, "name": "Crusader States", "url": "https://www.academia.edu/Documents/in/Crusader_States?f_ri=332912"}, {"id": 46796, "name": "Medieval Warfare", "url": "https://www.academia.edu/Documents/in/Medieval_Warfare?f_ri=332912"}, {"id": 51858, "name": "Jihad", "url": "https://www.academia.edu/Documents/in/Jihad?f_ri=332912"}, {"id": 80338, "name": "Ibn Taymiyya", "url": "https://www.academia.edu/Documents/in/Ibn_Taymiyya?f_ri=332912"}, {"id": 102705, "name": "Medieval Weapons and Equipment", "url": "https://www.academia.edu/Documents/in/Medieval_Weapons_and_Equipment?f_ri=332912"}, {"id": 169060, "name": "Salafi-Jihadi Ideology", "url": "https://www.academia.edu/Documents/in/Salafi-Jihadi_Ideology?f_ri=332912"}, {"id": 332912, "name": "Islamic military history", "url": "https://www.academia.edu/Documents/in/Islamic_military_history?f_ri=332912"}, {"id": 448365, "name": "Mongols and Mamluks", "url": "https://www.academia.edu/Documents/in/Mongols_and_Mamluks?f_ri=332912"}, {"id": 489338, "name": "Reception of Ibn Taymiyya between the 13th and 16th centuries", "url": "https://www.academia.edu/Documents/in/Reception_of_Ibn_Taymiyya_between_the_13th_and_16th_centuries?f_ri=332912"}, {"id": 699583, "name": "Armenian Kingdom of Cilicia", "url": "https://www.academia.edu/Documents/in/Armenian_Kingdom_of_Cilicia?f_ri=332912"}, {"id": 709694, "name": "Crusaders and Armenian Kingdom of Cilicia", "url": "https://www.academia.edu/Documents/in/Crusaders_and_Armenian_Kingdom_of_Cilicia?f_ri=332912"}, {"id": 804366, "name": "Medieval Siege Warfare", "url": "https://www.academia.edu/Documents/in/Medieval_Siege_Warfare?f_ri=332912"}, {"id": 1265320, "name": "Military History of the Islamic World", "url": "https://www.academia.edu/Documents/in/Military_History_of_the_Islamic_World?f_ri=332912"}, {"id": 1952102, "name": "The Fortifications of Armenian kingdom of Cilicia", "url": "https://www.academia.edu/Documents/in/The_Fortifications_of_Armenian_kingdom_of_Cilicia?f_ri=332912"}, {"id": 2873882, "name": "Mongols and crusaders ", "url": "https://www.academia.edu/Documents/in/Mongols_and_crusaders?f_ri=332912"}]}, {"id": 70284831, "title": "Les Mamelouks\u00a0: les cavaliers de l\u2019Islam. \u00c9tudes sur l\u2019art de la guerre chez les Mamelouks (XIIIe-XIVe si\u00e8cles), Paris, H\u00e9ritage, 2022.", "created_at": "2022-02-02T14:07:27.619-08:00", "url": "https://www.academia.edu/70284831/Les_Mamelouks_les_cavaliers_de_l_Islam_%C3%89tudes_sur_l_art_de_la_guerre_chez_les_Mamelouks_XIIIe_XIVe_si%C3%A8cles_Paris_H%C3%A9ritage_2022?f_ri=332912", "dom_id": "work_70284831", "summary": "Originaire pour la plupart des steppes eurasiatiques du Kipchak, r\u00e9gion r\u00e9put\u00e9e pour son peuple de cavaliers, et achet\u00e9s pour \u00eatre form\u00e9s \u00e0 la guerre, ceux qu\u2019on appelle les Mamelouks furent propuls\u00e9s sur le devant de la sc\u00e8ne dans le sillage de la septi\u00e8me croisade. Qui aurait pu penser que c\u2019est sur les \u00e9paules de ces esclaves-soldats \u00e9trangers et nouvellement convertis \u00e0 l\u2019islam que le sort de territoires de l\u2019Islam allait reposer pendant plusieurs d\u00e9cennies\u00a0? Et pourtant, ce sont bien les Mamelouks qui, dix ans \u00e0 peine apr\u00e8s leur prise du pouvoir en Egypte, port\u00e8rent pour un temps l\u2019\u00e9tendard de l\u2019Islam lequel mena\u00e7ait de tomber face \u00e0 divers dangers ext\u00e9rieurs. En un peu plus d\u2019un demi-si\u00e8cle, les Mamelouks r\u00e9ussirent l\u00e0 o\u00f9 beaucoup d\u2019autres dynasties musulmanes \u00e9chou\u00e8rent\u00a0: ils r\u00e9ussirent \u00e0 mettre fin \u00e0 l'existence des \u00c9tats latins d\u2019Orient, au royaume d\u2019Arm\u00e9nie-Cilicie, \u00e0 soumettre le royaume de Nubie et, surtout, \u00e0 arr\u00eater les invasions mongoles. Ce dernier exploit est, en grande partie, \u00e0 l\u2019origine du prestige et de la r\u00e9putation militaire des Mamelouks. Au cours des XIIIe et XIVe si\u00e8cles, les sultans et \u00e9mirs mamelouks mirent sur pied l\u2019une des arm\u00e9es les plus puissantes du Proche-Orient. Plus qu\u2019un m\u00e9tier, la guerre \u00e9tait la raison d\u2019\u00eatre des Mamelouks. A partir de l\u2019analyse et de la confrontation des sources arabes, latines, arm\u00e9niennes et persanes, Mehdi Berriah a r\u00e9alis\u00e9 plusieurs \u00e9tudes sur l\u2019art de la guerre de ces cavaliers hors pair dont certaines sont rassembl\u00e9es dans cet ouvrage.", "downloadable_attachments": [{"id": 80099421, "asset_id": 70284831, "asset_type": "Work", "always_allow_download": false}], "ordered_authors": [{"id": 10670362, "first_name": "Mehdi", "last_name": "BERRIAH", "domain_name": "independent", "page_name": "mehdiBERRIAH", "display_name": "Mehdi BERRIAH", "profile_url": "https://independent.academia.edu/mehdiBERRIAH?f_ri=332912", "photo": "https://0.academia-photos.com/10670362/15596225/35752039/s65_mehdi.berriah.jpg"}], "research_interests": [{"id": 6502, "name": "Mamluk Studies", "url": "https://www.academia.edu/Documents/in/Mamluk_Studies?f_ri=332912", "nofollow": false}, {"id": 16155, "name": "Mamluk History", "url": "https://www.academia.edu/Documents/in/Mamluk_History?f_ri=332912", "nofollow": false}, {"id": 30702, "name": "Mamluks (Islamic History)", "url": "https://www.academia.edu/Documents/in/Mamluks_Islamic_History_?f_ri=332912", "nofollow": false}, {"id": 67861, "name": "Medieval Military History", "url": "https://www.academia.edu/Documents/in/Medieval_Military_History?f_ri=332912", "nofollow": false}, {"id": 78805, "name": "Mamluk-Kipchak", "url": "https://www.academia.edu/Documents/in/Mamluk-Kipchak?f_ri=332912"}, {"id": 137380, "name": "Mamluk Cairo", "url": "https://www.academia.edu/Documents/in/Mamluk_Cairo?f_ri=332912"}, {"id": 268338, "name": "Baybars Mamluk", "url": "https://www.academia.edu/Documents/in/Baybars_Mamluk?f_ri=332912"}, {"id": 332912, "name": "Islamic military history", "url": "https://www.academia.edu/Documents/in/Islamic_military_history?f_ri=332912"}, {"id": 448365, "name": "Mongols and Mamluks", "url": "https://www.academia.edu/Documents/in/Mongols_and_Mamluks?f_ri=332912"}, {"id": 524423, "name": "Mamluks", "url": "https://www.academia.edu/Documents/in/Mamluks?f_ri=332912"}, {"id": 562473, "name": "Furusiyya", "url": "https://www.academia.edu/Documents/in/Furusiyya?f_ri=332912"}, {"id": 562474, "name": "Furusiyah", "url": "https://www.academia.edu/Documents/in/Furusiyah?f_ri=332912"}, {"id": 562477, "name": "Mamluk Furusiyya", "url": "https://www.academia.edu/Documents/in/Mamluk_Furusiyya?f_ri=332912"}, {"id": 666018, "name": "The Mamluk Sultanate", "url": "https://www.academia.edu/Documents/in/The_Mamluk_Sultanate?f_ri=332912"}, {"id": 1143007, "name": "Mamelouks", "url": "https://www.academia.edu/Documents/in/Mamelouks?f_ri=332912"}, {"id": 1265320, "name": "Military History of the Islamic World", "url": "https://www.academia.edu/Documents/in/Military_History_of_the_Islamic_World?f_ri=332912"}, {"id": 2517518, "name": "Bahriyya mamluks", "url": "https://www.academia.edu/Documents/in/Bahriyya_mamluks?f_ri=332912"}, {"id": 2620764, "name": "History and historiography of the Mamluks", "url": "https://www.academia.edu/Documents/in/History_and_historiography_of_the_Mamluks?f_ri=332912"}, {"id": 2990442, "name": "Mamelouk", "url": "https://www.academia.edu/Documents/in/Mamelouk?f_ri=332912"}]}, {"id": 31286319, "title": "Mehdi Berriah, \"Le cheval arabe chez les Mamelouks, entre pragmatisme, symboles et repr\u00e9sentations\", Arabian Humanities 8, 2017 (open access)", "created_at": "2017-02-07T13:10:44.907-08:00", "url": "https://www.academia.edu/31286319/Mehdi_Berriah_Le_cheval_arabe_chez_les_Mamelouks_entre_pragmatisme_symboles_et_repr%C3%A9sentations_Arabian_Humanities_8_2017_open_access_?f_ri=332912", "dom_id": "work_31286319", "summary": null, "downloadable_attachments": [{"id": 55287442, "asset_id": 31286319, "asset_type": "Work", "always_allow_download": false}, {"id": 53960879, "asset_id": 31286319, "asset_type": "Work", "always_allow_download": false}], "ordered_authors": [{"id": 10670362, "first_name": "Mehdi", "last_name": "BERRIAH", "domain_name": "independent", "page_name": "mehdiBERRIAH", "display_name": "Mehdi BERRIAH", "profile_url": "https://independent.academia.edu/mehdiBERRIAH?f_ri=332912", "photo": "https://0.academia-photos.com/10670362/15596225/35752039/s65_mehdi.berriah.jpg"}], "research_interests": [{"id": 6502, "name": "Mamluk Studies", "url": "https://www.academia.edu/Documents/in/Mamluk_Studies?f_ri=332912", "nofollow": false}, {"id": 16155, "name": "Mamluk History", "url": "https://www.academia.edu/Documents/in/Mamluk_History?f_ri=332912", "nofollow": false}, {"id": 25118, "name": "Medieval Islamic History", "url": "https://www.academia.edu/Documents/in/Medieval_Islamic_History?f_ri=332912", "nofollow": false}, {"id": 218928, "name": "Medieval Equestrian Studies", "url": "https://www.academia.edu/Documents/in/Medieval_Equestrian_Studies?f_ri=332912", "nofollow": false}, {"id": 332912, "name": "Islamic military history", "url": "https://www.academia.edu/Documents/in/Islamic_military_history?f_ri=332912"}, {"id": 562477, "name": "Mamluk Furusiyya", "url": "https://www.academia.edu/Documents/in/Mamluk_Furusiyya?f_ri=332912"}, {"id": 894220, "name": "Islamic warfare", "url": "https://www.academia.edu/Documents/in/Islamic_warfare?f_ri=332912"}]}, {"id": 40676524, "title": "Catatan Shaykh Wan Ahmad al-Fatani mengenai Sejarah Ketenteraan \u2018Uthmaniyyah dalam Kitab Hadiqat al-Azhar wa al-Rayyahin [Shaykh Wan Ahmad al-Fatani's Notes on Ottoman Military History in Hadiqat al-Azhar wa al-Rayyahin]", "created_at": "2019-10-20T05:36:45.676-07:00", "url": "https://www.academia.edu/40676524/Catatan_Shaykh_Wan_Ahmad_al_Fatani_mengenai_Sejarah_Ketenteraan_Uthmaniyyah_dalam_Kitab_Hadiqat_al_Azhar_wa_al_Rayyahin_Shaykh_Wan_Ahmad_al_Fatanis_Notes_on_Ottoman_Military_History_in_Hadiqat_al_Azhar_wa_al_Rayyahin_?f_ri=332912", "dom_id": "work_40676524", "summary": null, "downloadable_attachments": [{"id": 60959107, "asset_id": 40676524, "asset_type": "Work", "always_allow_download": false}], "ordered_authors": [{"id": 5811644, "first_name": "Ahmad Faathin", "last_name": "Mohd. Fadzil", "domain_name": "ukm-my", "page_name": "AhmadFaathinMohdFadzil", "display_name": "Ahmad Faathin Mohd. Fadzil", "profile_url": "https://ukm-my.academia.edu/AhmadFaathinMohdFadzil?f_ri=332912", "photo": "https://0.academia-photos.com/5811644/2498881/30223952/s65_ahmad_faathin.mohd._fadzil.jpg"}], "research_interests": [{"id": 45018, "name": "Islamic History and Muslim Civilization", "url": "https://www.academia.edu/Documents/in/Islamic_History_and_Muslim_Civilization?f_ri=332912", "nofollow": false}, {"id": 102363, "name": "Malay Studies", "url": "https://www.academia.edu/Documents/in/Malay_Studies?f_ri=332912", "nofollow": false}, {"id": 165257, "name": "Islamic Historiography", "url": "https://www.academia.edu/Documents/in/Islamic_Historiography?f_ri=332912", "nofollow": false}, {"id": 332912, "name": "Islamic military history", "url": "https://www.academia.edu/Documents/in/Islamic_military_history?f_ri=332912", "nofollow": false}, {"id": 3416199, "name": "Malay Scholar", "url": "https://www.academia.edu/Documents/in/Malay_Scholar?f_ri=332912"}, {"id": 3416200, "name": "Malay Ulema", "url": "https://www.academia.edu/Documents/in/Malay_Ulema?f_ri=332912"}]}, {"id": 31286291, "title": "\u00ab La conduite de la guerre de l\u2019arm\u00e9e mamelouke face aux Mongols (XIIIe-XIVe si\u00e8cle) \u00bb, Actes du 16e colloque international du d\u00e9partement des sciences historiques de l\u2019universit\u00e9 de Laval, 17-19 f\u00e9vrier 2016, Presses de l\u2019Universit\u00e9 de Laval, Qu\u00e9bec, 2017, p. 131-154", "created_at": "2017-02-07T13:07:37.015-08:00", "url": "https://www.academia.edu/31286291/_La_conduite_de_la_guerre_de_l_arm%C3%A9e_mamelouke_face_aux_Mongols_XIIIe_XIVe_si%C3%A8cle_Actes_du_16e_colloque_international_du_d%C3%A9partement_des_sciences_historiques_de_l_universit%C3%A9_de_Laval_17_19_f%C3%A9vrier_2016_Presses_de_l_Universit%C3%A9_de_Laval_Qu%C3%A9bec_2017_p_131_154?f_ri=332912", "dom_id": "work_31286291", "summary": null, "downloadable_attachments": [{"id": 53129897, "asset_id": 31286291, "asset_type": "Work", "always_allow_download": false}], "ordered_authors": [{"id": 10670362, "first_name": "Mehdi", "last_name": "BERRIAH", "domain_name": "independent", "page_name": "mehdiBERRIAH", "display_name": "Mehdi BERRIAH", "profile_url": "https://independent.academia.edu/mehdiBERRIAH?f_ri=332912", "photo": "https://0.academia-photos.com/10670362/15596225/35752039/s65_mehdi.berriah.jpg"}], "research_interests": [{"id": 133, "name": "Military History", "url": "https://www.academia.edu/Documents/in/Military_History?f_ri=332912", "nofollow": false}, {"id": 579, "name": "Strategy (Military Science)", "url": "https://www.academia.edu/Documents/in/Strategy_Military_Science_?f_ri=332912", "nofollow": false}, {"id": 1446, "name": "Medieval History", "url": "https://www.academia.edu/Documents/in/Medieval_History?f_ri=332912", "nofollow": false}, {"id": 6502, "name": "Mamluk Studies", "url": "https://www.academia.edu/Documents/in/Mamluk_Studies?f_ri=332912", "nofollow": false}, {"id": 15800, "name": "Islamic History", "url": "https://www.academia.edu/Documents/in/Islamic_History?f_ri=332912"}, {"id": 16155, "name": "Mamluk History", "url": "https://www.academia.edu/Documents/in/Mamluk_History?f_ri=332912"}, {"id": 30702, "name": "Mamluks (Islamic History)", "url": "https://www.academia.edu/Documents/in/Mamluks_Islamic_History_?f_ri=332912"}, {"id": 332912, "name": "Islamic military history", "url": "https://www.academia.edu/Documents/in/Islamic_military_history?f_ri=332912"}, {"id": 448365, "name": "Mongols and Mamluks", "url": "https://www.academia.edu/Documents/in/Mongols_and_Mamluks?f_ri=332912"}, {"id": 2899814, "name": "Medieval Islamic and Turco-Iranian world, Mongol world empire", "url": "https://www.academia.edu/Documents/in/Medieval_Islamic_and_Turco-Iranian_world_Mongol_world_empire?f_ri=332912"}, {"id": 2899815, "name": "Seljuk, Mongol, post-Mongol, and Ottoman Anatolia (1200-1500)", "url": "https://www.academia.edu/Documents/in/Seljuk_Mongol_post-Mongol_and_Ottoman_Anatolia_1200-1500_?f_ri=332912"}, {"id": 2899816, "name": "Comparative empire, frontier, and political culture", "url": "https://www.academia.edu/Documents/in/Comparative_empire_frontier_and_political_culture?f_ri=332912"}, {"id": 2899817, "name": "Persian and Ottoman Turkish historical writing", "url": "https://www.academia.edu/Documents/in/Persian_and_Ottoman_Turkish_historical_writing?f_ri=332912"}]}, {"id": 75142250, "title": "\"La fin des Etats latins\", in Atlas des mondes m\u00e9di\u00e9vaux musulmans, Sylvie Denoix et H\u00e9l\u00e8ne Renel (eds.), Paris, CNRS Editions, 2022, p. 296-297", "created_at": "2022-04-01T04:15:05.236-07:00", "url": "https://www.academia.edu/75142250/_La_fin_des_Etats_latins_in_Atlas_des_mondes_m%C3%A9di%C3%A9vaux_musulmans_Sylvie_Denoix_et_H%C3%A9l%C3%A8ne_Renel_eds_Paris_CNRS_Editions_2022_p_296_297?f_ri=332912", "dom_id": "work_75142250", "summary": null, "downloadable_attachments": [{"id": 83030312, "asset_id": 75142250, "asset_type": "Work", "always_allow_download": false}], "ordered_authors": [{"id": 10670362, "first_name": "Mehdi", "last_name": "BERRIAH", "domain_name": "independent", "page_name": "mehdiBERRIAH", "display_name": "Mehdi BERRIAH", "profile_url": "https://independent.academia.edu/mehdiBERRIAH?f_ri=332912", "photo": "https://0.academia-photos.com/10670362/15596225/35752039/s65_mehdi.berriah.jpg"}], "research_interests": [{"id": 6502, "name": "Mamluk Studies", "url": "https://www.academia.edu/Documents/in/Mamluk_Studies?f_ri=332912", "nofollow": false}, {"id": 16155, "name": "Mamluk History", "url": "https://www.academia.edu/Documents/in/Mamluk_History?f_ri=332912", "nofollow": false}, {"id": 30702, "name": "Mamluks (Islamic History)", "url": "https://www.academia.edu/Documents/in/Mamluks_Islamic_History_?f_ri=332912", "nofollow": false}, {"id": 35316, "name": "Crusades and the Latin East", "url": "https://www.academia.edu/Documents/in/Crusades_and_the_Latin_East?f_ri=332912", "nofollow": false}, {"id": 42271, "name": "Crusader States", "url": "https://www.academia.edu/Documents/in/Crusader_States?f_ri=332912"}, {"id": 46796, "name": "Medieval Warfare", "url": "https://www.academia.edu/Documents/in/Medieval_Warfare?f_ri=332912"}, {"id": 67861, "name": "Medieval Military History", "url": "https://www.academia.edu/Documents/in/Medieval_Military_History?f_ri=332912"}, {"id": 95298, "name": "Crusaders", "url": "https://www.academia.edu/Documents/in/Crusaders?f_ri=332912"}, {"id": 101053, "name": "Siege Warfare", "url": "https://www.academia.edu/Documents/in/Siege_Warfare?f_ri=332912"}, {"id": 268338, "name": "Baybars Mamluk", "url": "https://www.academia.edu/Documents/in/Baybars_Mamluk?f_ri=332912"}, {"id": 325126, "name": "History of the Crusades and the Latin East", "url": "https://www.academia.edu/Documents/in/History_of_the_Crusades_and_the_Latin_East?f_ri=332912"}, {"id": 332912, "name": "Islamic military history", "url": "https://www.academia.edu/Documents/in/Islamic_military_history?f_ri=332912"}, {"id": 666018, "name": "The Mamluk Sultanate", "url": "https://www.academia.edu/Documents/in/The_Mamluk_Sultanate?f_ri=332912"}, {"id": 804366, "name": "Medieval Siege Warfare", "url": "https://www.academia.edu/Documents/in/Medieval_Siege_Warfare?f_ri=332912"}, {"id": 894220, "name": "Islamic warfare", "url": "https://www.academia.edu/Documents/in/Islamic_warfare?f_ri=332912"}, {"id": 1265320, "name": "Military History of the Islamic World", "url": "https://www.academia.edu/Documents/in/Military_History_of_the_Islamic_World?f_ri=332912"}, {"id": 2477007, "name": "Turks and Crusaders", "url": "https://www.academia.edu/Documents/in/Turks_and_Crusaders?f_ri=332912"}, {"id": 2830927, "name": "Sultan Baybars", "url": "https://www.academia.edu/Documents/in/Sultan_Baybars?f_ri=332912"}, {"id": 2838656, "name": "Baybars", "url": "https://www.academia.edu/Documents/in/Baybars?f_ri=332912"}]}, {"id": 44635775, "title": "\"Repr\u00e9sentations, sunnanisation et sacralisation de la fur\u016bsiyya \u00e0 l'\u00e9poque mamelouke (xiii e -xvi e si\u00e8cle)\", Bulletin d'\u00e9tudes orientales, Presses de l'Ifpo, Beyrouth, 2020, p. 229-246", "created_at": "2020-12-04T08:19:42.017-08:00", "url": "https://www.academia.edu/44635775/_Repr%C3%A9sentations_sunnanisation_et_sacralisation_de_la_fur%C5%ABsiyya_%C3%A0_l%C3%A9poque_mamelouke_xiii_e_xvi_e_si%C3%A8cle_Bulletin_d%C3%A9tudes_orientales_Presses_de_lIfpo_Beyrouth_2020_p_229_246?f_ri=332912", "dom_id": "work_44635775", "summary": "Unrivaled cavalrymen, the Mamluks were the undisputed masters of the fur\u016bsiyya in their time. Fur\u016bsiyya art was the result of a combination of different equestrian and military traditions. As argued by A. Carayon in 2012, this art reached its peak under the Mamluks and became a channel of social distinction. This article examines various aspects of the practice of fur\u016bsiyya beyond military parades and competitions that were practiced by Mamluk legions. Did the passion for fur\u016bsiyya only exist among the Mamluks or did its practice extend to other social groups? As such, how did this interest in fur\u016bsiyya transcend social boundaries? Was it practiced only as a military art? Did the practice of the fur\u016bsiyya mean more to the Mamluks than mere military training and a channel to social distinction? These are some of the questions that I will attempt to answer in this discussion based on the analysis of various sources including chronicles, instruction and training manuals, and religious treatises.", "downloadable_attachments": [{"id": 65106358, "asset_id": 44635775, "asset_type": "Work", "always_allow_download": false}], "ordered_authors": [{"id": 10670362, "first_name": "Mehdi", "last_name": "BERRIAH", "domain_name": "independent", "page_name": "mehdiBERRIAH", "display_name": "Mehdi BERRIAH", "profile_url": "https://independent.academia.edu/mehdiBERRIAH?f_ri=332912", "photo": "https://0.academia-photos.com/10670362/15596225/35752039/s65_mehdi.berriah.jpg"}], "research_interests": [{"id": 540, "name": "Islamic Law", "url": "https://www.academia.edu/Documents/in/Islamic_Law?f_ri=332912", "nofollow": false}, {"id": 6502, "name": "Mamluk Studies", "url": "https://www.academia.edu/Documents/in/Mamluk_Studies?f_ri=332912", "nofollow": false}, {"id": 16155, "name": "Mamluk History", "url": "https://www.academia.edu/Documents/in/Mamluk_History?f_ri=332912", "nofollow": false}, {"id": 80338, "name": "Ibn Taymiyya", "url": "https://www.academia.edu/Documents/in/Ibn_Taymiyya?f_ri=332912", "nofollow": false}, {"id": 207493, "name": "Ibn Qayyim al-Jawziyya", "url": "https://www.academia.edu/Documents/in/Ibn_Qayyim_al-Jawziyya?f_ri=332912"}, {"id": 268338, "name": "Baybars Mamluk", "url": "https://www.academia.edu/Documents/in/Baybars_Mamluk?f_ri=332912"}, {"id": 293905, "name": "Sunna", "url": "https://www.academia.edu/Documents/in/Sunna?f_ri=332912"}, {"id": 332912, "name": "Islamic military history", "url": "https://www.academia.edu/Documents/in/Islamic_military_history?f_ri=332912"}, {"id": 562473, "name": "Furusiyya", "url": "https://www.academia.edu/Documents/in/Furusiyya?f_ri=332912"}, {"id": 562474, "name": "Furusiyah", "url": "https://www.academia.edu/Documents/in/Furusiyah?f_ri=332912"}, {"id": 562477, "name": "Mamluk Furusiyya", "url": "https://www.academia.edu/Documents/in/Mamluk_Furusiyya?f_ri=332912"}, {"id": 580268, "name": "ibn Taymiyyah", "url": "https://www.academia.edu/Documents/in/ibn_Taymiyyah?f_ri=332912"}, {"id": 1125207, "name": "Ibn Qayyim Al-Jawziyya Ibn Taymiyya", "url": "https://www.academia.edu/Documents/in/Ibn_Qayyim_Al-Jawziyya_Ibn_Taymiyya?f_ri=332912"}, {"id": 1223709, "name": "Islamic law and jurisprudence", "url": "https://www.academia.edu/Documents/in/Islamic_law_and_jurisprudence-1?f_ri=332912"}, {"id": 1265320, "name": "Military History of the Islamic World", "url": "https://www.academia.edu/Documents/in/Military_History_of_the_Islamic_World?f_ri=332912"}, {"id": 1400668, "name": "Medieval Horse", "url": "https://www.academia.edu/Documents/in/Medieval_Horse?f_ri=332912"}, {"id": 1596345, "name": "Medieval Horsemanship", "url": "https://www.academia.edu/Documents/in/Medieval_Horsemanship?f_ri=332912"}, {"id": 2830927, "name": "Sultan Baybars", "url": "https://www.academia.edu/Documents/in/Sultan_Baybars?f_ri=332912"}, {"id": 3074983, "name": "Ibn Taymiyyah's", "url": "https://www.academia.edu/Documents/in/Ibn_Taymiyyahs?f_ri=332912"}, {"id": 3748010, "name": "Ibnu al Qayyim al Jauziyyah", "url": "https://www.academia.edu/Documents/in/Ibnu_al_Qayyim_al_Jauziyyah?f_ri=332912"}]}, {"id": 45002823, "title": "\u0130slam\u2019\u0131n Erken D\u00f6neminde \u015eam B\u00f6lgesindeki Asker\u00ee-\u0130dar\u00ee B\u00f6lgelerin (C\u00fcnd/Ecn\u00e2d) Olu\u015fumu ve Bizans (Do\u011fu Roma) Toprak Sisteminin Etkisi [Formation of Military-Administrative Districts (Jund/Ajn\u0101d) in Bil\u0101d al-Sh\u0101m During the Early Islamic Period and the Influence of the Byzantine Land Regime]", "created_at": "2021-01-28T22:07:48.791-08:00", "url": "https://www.academia.edu/45002823/%C4%B0slam_%C4%B1n_Erken_D%C3%B6neminde_%C5%9Eam_B%C3%B6lgesindeki_Asker%C3%AE_%C4%B0dar%C3%AE_B%C3%B6lgelerin_C%C3%BCnd_Ecn%C3%A2d_Olu%C5%9Fumu_ve_Bizans_Do%C4%9Fu_Roma_Toprak_Sisteminin_Etkisi_Formation_of_Military_Administrative_Districts_Jund_Ajn%C4%81d_in_Bil%C4%81d_al_Sh%C4%81m_During_the_Early_Islamic_Period_and_the_Influence_of_the_Byzantine_Land_Regime_?f_ri=332912", "dom_id": "work_45002823", "summary": "Muslims captured vast lands following the early conquests by the Prophet and first caliphs, extending their control beyond the Arabian Peninsula. They accommodated the local social, administrative, and cultural heritage in order to take control over the region. Just like all civilizational \u201cinteractions,\u201d certain practices remained similar to their earlier instantiations. One of these practices was the system of jund, which was applied following the conquest of Bil\u0101d al-Sh\u0101m (Greater Syria). Jund (pl. ajn\u0101d), literally meaning \u201carmy\u2014military districts,\u201d described military-administrative districts established in Bil\u0101d al-Sh\u0101m (a region covering Syria, Jordan, Palestine, Lebanon and southern Turkey) in early Islamic history.\nFull text is here: http://isad.isam.org.tr/vdata/sayi45/isad045_yilmaz.pdf", "downloadable_attachments": [{"id": 65549093, "asset_id": 45002823, "asset_type": "Work", "always_allow_download": false}], "ordered_authors": [{"id": 11762408, "first_name": "Halil \u0130brahim", "last_name": "Y\u0131lmaz", "domain_name": "sakarya", "page_name": "halilibrahimyilmaz", "display_name": "Halil \u0130brahim Y\u0131lmaz", "profile_url": "https://sakarya.academia.edu/halilibrahimyilmaz?f_ri=332912", "photo": "https://0.academia-photos.com/11762408/3387364/94229835/s65_halil_i_brahim.y_lmaz.jpg"}], "research_interests": [{"id": 10091, "name": "Byzantine Studies", "url": "https://www.academia.edu/Documents/in/Byzantine_Studies?f_ri=332912", "nofollow": false}, {"id": 15800, "name": "Islamic History", "url": "https://www.academia.edu/Documents/in/Islamic_History?f_ri=332912", "nofollow": false}, {"id": 25118, "name": "Medieval Islamic History", "url": "https://www.academia.edu/Documents/in/Medieval_Islamic_History?f_ri=332912", "nofollow": false}, {"id": 48301, "name": "Bilad Al-Sham", "url": "https://www.academia.edu/Documents/in/Bilad_Al-Sham?f_ri=332912", "nofollow": false}, {"id": 332912, "name": "Islamic military history", "url": "https://www.academia.edu/Documents/in/Islamic_military_history?f_ri=332912"}, {"id": 1118270, "name": "Islamic Culture and Civilization", "url": "https://www.academia.edu/Documents/in/Islamic_Culture_and_Civilization-1?f_ri=332912"}, {"id": 1134753, "name": "Land Regimes", "url": "https://www.academia.edu/Documents/in/Land_Regimes?f_ri=332912"}, {"id": 1248307, "name": "Byzantine Themata", "url": "https://www.academia.edu/Documents/in/Byzantine_Themata?f_ri=332912"}, {"id": 2196464, "name": "Ajnad al-Sham", "url": "https://www.academia.edu/Documents/in/Ajnad_al-Sham?f_ri=332912"}, {"id": 3872510, "name": "Jund", "url": "https://www.academia.edu/Documents/in/Jund?f_ri=332912"}]}, {"id": 5012885, "title": "The Ottoman Armies 1290-1453, article from Weapons and War Encyclopedia Revised Edition Volume 1. Ancient and Medieval Warfare ", "created_at": "2013-11-06T07:29:30.511-08:00", "url": "https://www.academia.edu/5012885/The_Ottoman_Armies_1290_1453_article_from_Weapons_and_War_Encyclopedia_Revised_Edition_Volume_1_Ancient_and_Medieval_Warfare?f_ri=332912", "dom_id": "work_5012885", "summary": null, "downloadable_attachments": [{"id": 33597853, "asset_id": 5012885, "asset_type": "Work", "always_allow_download": false}], "ordered_authors": [{"id": 1475416, "first_name": "James", "last_name": "Tallon", "domain_name": "lewisu", "page_name": "JamesTallon", "display_name": "James N Tallon", "profile_url": "https://lewisu.academia.edu/JamesTallon?f_ri=332912", "photo": "https://0.academia-photos.com/1475416/1356250/20808231/s65_james.tallon.jpg"}], "research_interests": [{"id": 133, "name": "Military History", "url": "https://www.academia.edu/Documents/in/Military_History?f_ri=332912", "nofollow": false}, {"id": 559, "name": "Military Science", "url": "https://www.academia.edu/Documents/in/Military_Science?f_ri=332912", "nofollow": false}, {"id": 1187, "name": "Ottoman History", "url": "https://www.academia.edu/Documents/in/Ottoman_History?f_ri=332912", "nofollow": false}, {"id": 1446, "name": "Medieval History", "url": "https://www.academia.edu/Documents/in/Medieval_History?f_ri=332912", "nofollow": false}, {"id": 6739, "name": "Medieval Islam", "url": "https://www.academia.edu/Documents/in/Medieval_Islam?f_ri=332912"}, {"id": 8122, "name": "Ottoman Studies", "url": "https://www.academia.edu/Documents/in/Ottoman_Studies?f_ri=332912"}, {"id": 8700, "name": "Turkish and Middle East Studies", "url": "https://www.academia.edu/Documents/in/Turkish_and_Middle_East_Studies?f_ri=332912"}, {"id": 9282, "name": "Turkish History", "url": "https://www.academia.edu/Documents/in/Turkish_History?f_ri=332912"}, {"id": 11208, "name": "Ottoman Empire", "url": "https://www.academia.edu/Documents/in/Ottoman_Empire?f_ri=332912"}, {"id": 25118, "name": "Medieval Islamic History", "url": "https://www.academia.edu/Documents/in/Medieval_Islamic_History?f_ri=332912"}, {"id": 26643, "name": "Ottoman Military History", "url": "https://www.academia.edu/Documents/in/Ottoman_Military_History?f_ri=332912"}, {"id": 28225, "name": "Medieval Balkans", "url": "https://www.academia.edu/Documents/in/Medieval_Balkans?f_ri=332912"}, {"id": 38513, "name": "Ottoman Military", "url": "https://www.academia.edu/Documents/in/Ottoman_Military?f_ri=332912"}, {"id": 46796, "name": "Medieval Warfare", "url": "https://www.academia.edu/Documents/in/Medieval_Warfare?f_ri=332912"}, {"id": 63961, "name": "Early Modern Warfare", "url": "https://www.academia.edu/Documents/in/Early_Modern_Warfare?f_ri=332912"}, {"id": 67861, "name": "Medieval Military History", "url": "https://www.academia.edu/Documents/in/Medieval_Military_History?f_ri=332912"}, {"id": 77533, "name": "Later Crusades", "url": "https://www.academia.edu/Documents/in/Later_Crusades?f_ri=332912"}, {"id": 87744, "name": "Ottoman miltiary history", "url": "https://www.academia.edu/Documents/in/Ottoman_miltiary_history?f_ri=332912"}, {"id": 100860, "name": "Medieval Middle east", "url": "https://www.academia.edu/Documents/in/Medieval_Middle_east?f_ri=332912"}, {"id": 111191, "name": "Early Ottoman Military History", "url": "https://www.academia.edu/Documents/in/Early_Ottoman_Military_History?f_ri=332912"}, {"id": 113114, "name": "Osmanl\u0131 Ordu", "url": "https://www.academia.edu/Documents/in/Osmanli_Ordu?f_ri=332912"}, {"id": 113499, "name": "Ottoman Military Matters", "url": "https://www.academia.edu/Documents/in/Ottoman_Military_Matters?f_ri=332912"}, {"id": 147797, "name": "Medieval Anatolia (Seljuk, Mongol)", "url": "https://www.academia.edu/Documents/in/Medieval_Anatolia_Seljuk_Mongol_?f_ri=332912"}, {"id": 155558, "name": "Military history of Ottoman empire", "url": "https://www.academia.edu/Documents/in/Military_history_of_Ottoman_empire?f_ri=332912"}, {"id": 216370, "name": "Orta\u00e7a\u011f Tarihi", "url": "https://www.academia.edu/Documents/in/Ortacag_Tarihi?f_ri=332912"}, {"id": 225732, "name": "Middle East Medieval history, Mamluk Kingdom, Ottoman Empire", "url": "https://www.academia.edu/Documents/in/Middle_East_Medieval_history_Mamluk_Kingdom_Ottoman_Empire?f_ri=332912"}, {"id": 274614, "name": "Askeri Tarih", "url": "https://www.academia.edu/Documents/in/Askeri_Tarih?f_ri=332912"}, {"id": 275853, "name": "Osmanli History", "url": "https://www.academia.edu/Documents/in/Osmanli_History?f_ri=332912"}, {"id": 282117, "name": "Osmanl\u0131 \u0130mparatorlu\u011fu", "url": "https://www.academia.edu/Documents/in/Osmanli_Imparatorlugu?f_ri=332912"}, {"id": 298348, "name": "Osmanl\u0131 Tarihi", "url": "https://www.academia.edu/Documents/in/Osmanl%C4%B1_Tarihi?f_ri=332912"}, {"id": 310469, "name": "Early Ottoman History", "url": "https://www.academia.edu/Documents/in/Early_Ottoman_History?f_ri=332912"}, {"id": 332912, "name": "Islamic military history", "url": "https://www.academia.edu/Documents/in/Islamic_military_history?f_ri=332912"}, {"id": 351017, "name": "Late Byzantine and Early Ottoman Era", "url": "https://www.academia.edu/Documents/in/Late_Byzantine_and_Early_Ottoman_Era?f_ri=332912"}, {"id": 367729, "name": "Turkish military", "url": "https://www.academia.edu/Documents/in/Turkish_military?f_ri=332912"}, {"id": 412673, "name": "History of Ottoman Military Structure", "url": "https://www.academia.edu/Documents/in/History_of_Ottoman_Military_Structure?f_ri=332912"}, {"id": 515485, "name": "Ottoman Anatolia (1200-1500) Comparative empire", "url": "https://www.academia.edu/Documents/in/Ottoman_Anatolia_1200-1500_Comparative_empire?f_ri=332912"}, {"id": 563781, "name": "Turkish military history", "url": "https://www.academia.edu/Documents/in/Turkish_military_history?f_ri=332912"}, {"id": 591343, "name": "Later crusade, Hunyadi expedition in Balkans (1443). Hungariam medieval military history. Ottoman medieval military history.", "url": "https://www.academia.edu/Documents/in/Later_crusade_Hunyadi_expedition_in_Balkans_1443_._Hungariam_medieval_military_history._Ottoman_me?f_ri=332912"}, {"id": 756047, "name": "Early Ottoman Sultans", "url": "https://www.academia.edu/Documents/in/Early_Ottoman_Sultans?f_ri=332912"}, {"id": 836917, "name": "Osmanl\u0131 Askeri Tarihi", "url": "https://www.academia.edu/Documents/in/Osmanli_Askeri_Tarihi?f_ri=332912"}, {"id": 1003725, "name": "Early Ottoman Times", "url": "https://www.academia.edu/Documents/in/Early_Ottoman_Times?f_ri=332912"}, {"id": 1009233, "name": "Battles of Nicopolis and Varna", "url": "https://www.academia.edu/Documents/in/Battles_of_Nicopolis_and_Varna?f_ri=332912"}, {"id": 1107366, "name": "Istorie Militara", "url": "https://www.academia.edu/Documents/in/Istorie_Militara?f_ri=332912"}, {"id": 1244961, "name": "Osmanl\u0131 Askeri Te\u015fkilat\u0131", "url": "https://www.academia.edu/Documents/in/Osmanli_Askeri_Teskilati?f_ri=332912"}, {"id": 1561014, "name": "Ottoman Army", "url": "https://www.academia.edu/Documents/in/Ottoman_Army?f_ri=332912"}, {"id": 2430183, "name": "Crusade of Varna", "url": "https://www.academia.edu/Documents/in/Crusade_of_Varna?f_ri=332912"}, {"id": 2899814, "name": "Medieval Islamic and Turco-Iranian world, Mongol world empire", "url": "https://www.academia.edu/Documents/in/Medieval_Islamic_and_Turco-Iranian_world_Mongol_world_empire?f_ri=332912"}, {"id": 2899815, "name": "Seljuk, Mongol, post-Mongol, and Ottoman Anatolia (1200-1500)", "url": "https://www.academia.edu/Documents/in/Seljuk_Mongol_post-Mongol_and_Ottoman_Anatolia_1200-1500_?f_ri=332912"}, {"id": 2899816, "name": "Comparative empire, frontier, and political culture", "url": "https://www.academia.edu/Documents/in/Comparative_empire_frontier_and_political_culture?f_ri=332912"}, {"id": 2899817, "name": "Persian and Ottoman Turkish historical writing", "url": "https://www.academia.edu/Documents/in/Persian_and_Ottoman_Turkish_historical_writing?f_ri=332912"}]}, {"id": 37572244, "title": "Buhara Hanl\u0131\u011f\u0131'n\u0131n Askeri Te\u015fkilat\u0131 (1500-1868)", "created_at": "2018-10-12T01:58:47.540-07:00", "url": "https://www.academia.edu/37572244/Buhara_Hanl%C4%B1%C4%9F%C4%B1n%C4%B1n_Askeri_Te%C5%9Fkilat%C4%B1_1500_1868_?f_ri=332912", "dom_id": "work_37572244", "summary": "Buhara \u00d6zbek Hanl\u0131\u011f\u0131 1500 y\u0131l\u0131nda \u00c7ingiz Han\u2019\u0131n o\u011flu Cuci soyundan gelen \u015eibanl\u0131lar s\u00fclalesinden Muhammed \u015eibani Han taraf\u0131ndan Mavera\u00fcnnehr\u2019de kurulmu\u015f, k\u0131sa s\u00fcrede Bat\u0131 T\u00fcrkistan\u2019\u0131n h\u00e2kimi olmu\u015f ve daha sonra s\u0131n\u0131rlar\u0131 k\u00fc\u00e7\u00fclse de XIX. asr\u0131n ortalar\u0131na kadar ba\u011f\u0131ms\u0131z bir \u015fekilde varl\u0131\u011f\u0131n\u0131 s\u00fcrd\u00fcrm\u00fc\u015ft\u00fcr. Devletin askeri g\u00fcc\u00fcn\u00fcn temeli kurulu\u015f a\u015famas\u0131ndan itibaren \u00d6zbek ulusunu olu\u015fturan kabile birliklerine dayanmaktad\u0131r. Bunun yan\u0131 s\u0131ra \u00d6zbeklerden ve ba\u015fka topluluklardan sa\u011flanan insan unsuru ile hassa birlikleri olu\u015fturulmu\u015f ve ayr\u0131ca Kazak, K\u0131rg\u0131z, Karakalpak ve T\u00fcrkmenler gibi devletin idaresi alt\u0131nda bulunan topluluklardan da yard\u0131mc\u0131 birlikler sa\u011flanm\u0131\u015ft\u0131r. Buhara \u00d6zbek ordusu, \u00c7ingiz Han\u2019dan sonra kurulan T\u00fcrk-Mo\u011fol k\u00f6kenli devletlerin askeri m\u00fcesseselerinden b\u00fcy\u00fck oranda etkilenmi\u015ftir. Askeri terimler ve askeri birimler b\u00fcy\u00fck oranda Alt\u0131norda Hanl\u0131\u011f\u0131, \u0130lhanl\u0131lar ve Timurlulardan miras al\u0131nm\u0131\u015ft\u0131r. Buhara \u00d6zbek Hanl\u0131\u011f\u0131\u2019ndan sonra T\u00fcrkistan\u2019da kurulan Hive ve Hokand Hanl\u0131klar\u0131n\u0131n askeri m\u00fcesseselerinde de bu yap\u0131n\u0131n etkisi g\u00f6r\u00fclmektedir. Ne var ki klasik Orta\u00e7a\u011f T\u00fcrk-Mo\u011fol ordu gelene\u011fi \u00fczerine \u015fekillenen Buhara \u00d6zbek ordusu, XVI. as\u0131rda etkin bir muharip g\u00fc\u00e7 olsa da, XVII. as\u0131rdan itibaren Orta Asya\u2019n\u0131n siyasi, iktisadi ve k\u00fclt\u00fcrel gerilemesine paralel olarak XIX. asr\u0131n ortalar\u0131na kadar pek bir geli\u015fim g\u00f6sterememi\u015f, modern d\u00fcnyan\u0131n askeri sisteminin \u00e7ok gerisinde kalm\u0131\u015ft\u0131r. Bu durum XVIII. ve XIX. as\u0131rlarda devleti istilalara kar\u015f\u0131 savunmas\u0131z b\u0131rakm\u0131\u015ft\u0131r.    \n\nBukhara Uzbek Khanate was founded in 1500 in Transoxiana by Muhammed Shibani Khan from Shibanid Dynasty, which descends from Jochi, son of Genghis Khan, and in short time frame dominated West Turkestan and albeit its territory shrinking afterwards, it continued its sovereign existence upto the middle of the XIX century. From the beginning, foundation of the state\u2019s military power was based on tribal unions comprising Uzbek Ulus. Alongside this, royal units were formed from elements obtained from Uzbeks and other groups and furthermore, auxiliary forces were provided by communities like Kazakhs, Kyrgyz, Karakalpaks and Turkmens who were under the state\u2019s control. Bukharan Uzbek Army was influenced to a great extend by military institutions of Turko-Mongol states founded after Genghis Khan. Military terminology and military units were largely inherited from Golden Horde, Ilkhanates and Timurids. The influence of this organisation is also seen in military establishments of Khiva and Hokand Khanates, which were founded in Turkestan after Bukhara Uzbek Khanate. Yet, eventhough Bukharan Uzbek Army, which was formed on the classical Medieval Turko-Mongol military tradition, was an effective combat force in XVIth century, from XVIIth century on wards and upto the middle of XIXth century, in paralel to Central Asia\u2019s political, economic and cultural regression, it couldn\u2019t make any progress and heavily lagged behind modern world\u2019s military system. This condition left the state defenceless against invasions in XVIIIth and XVIIIth centuries.", "downloadable_attachments": [{"id": 57549813, "asset_id": 37572244, "asset_type": "Work", "always_allow_download": false}], "ordered_authors": [{"id": 25281783, "first_name": "Selim Serkan", "last_name": "\u00dckten", "domain_name": "aksaray", "page_name": "Serkan\u00dckten", "display_name": "Selim Serkan \u00dckten", "profile_url": "https://aksaray.academia.edu/Serkan%C3%9Ckten?f_ri=332912", "photo": "https://0.academia-photos.com/25281783/6879733/18172823/s65_serkan._kten.jpg"}], "research_interests": [{"id": 205471, "name": "Turkestan", "url": "https://www.academia.edu/Documents/in/Turkestan?f_ri=332912", "nofollow": false}, {"id": 332912, "name": "Islamic military history", "url": "https://www.academia.edu/Documents/in/Islamic_military_history?f_ri=332912", "nofollow": false}, {"id": 562476, "name": "Mongol Military History", "url": "https://www.academia.edu/Documents/in/Mongol_Military_History?f_ri=332912", "nofollow": false}, {"id": 1006156, "name": "Uzbeks", "url": "https://www.academia.edu/Documents/in/Uzbeks?f_ri=332912", "nofollow": false}, {"id": 1006161, "name": "Bukhara Khanate", "url": "https://www.academia.edu/Documents/in/Bukhara_Khanate?f_ri=332912"}, {"id": 1535566, "name": "Shaybanids", "url": "https://www.academia.edu/Documents/in/Shaybanids?f_ri=332912"}, {"id": 2063026, "name": "Shaybanid Dynasty", "url": "https://www.academia.edu/Documents/in/Shaybanid_Dynasty?f_ri=332912"}, {"id": 2469775, "name": "T\u00fcrk Ordusu", "url": "https://www.academia.edu/Documents/in/T%C3%BCrk_Ordusu?f_ri=332912"}, {"id": 2571199, "name": "Manghits (Islamic History)", "url": "https://www.academia.edu/Documents/in/Manghits_Islamic_History_?f_ri=332912"}, {"id": 3039165, "name": "Military History of Turkestan", "url": "https://www.academia.edu/Documents/in/Military_History_of_Turkestan?f_ri=332912"}, {"id": 3039166, "name": "astrakhan dynasty", "url": "https://www.academia.edu/Documents/in/astrakhan_dynasty?f_ri=332912"}, {"id": 3039167, "name": "turkish-mongol military", "url": "https://www.academia.edu/Documents/in/turkish-mongol_military?f_ri=332912"}, {"id": 3039168, "name": "turkestan khanates", "url": "https://www.academia.edu/Documents/in/turkestan_khanates?f_ri=332912"}, {"id": 3039169, "name": "Buhara \u00d6zbek Hanl\u0131\u011f\u0131", "url": "https://www.academia.edu/Documents/in/Buhara_%C3%96zbek_Hanl%C4%B1%C4%9F%C4%B1?f_ri=332912"}, {"id": 3039170, "name": "\u015eibaniler", "url": "https://www.academia.edu/Documents/in/%C5%9Eibaniler?f_ri=332912"}, {"id": 3039171, "name": "\u015eeyb\u00e2n\u00eeler", "url": "https://www.academia.edu/Documents/in/%C5%9Eeyb%C3%A2n%C3%AEler?f_ri=332912"}, {"id": 3039172, "name": "Mang\u0131tlar", "url": "https://www.academia.edu/Documents/in/Mang%C4%B1tlar?f_ri=332912"}, {"id": 3039173, "name": "T\u00fcrkistan Sava\u015f Sanat\u0131", "url": "https://www.academia.edu/Documents/in/T%C3%BCrkistan_Sava%C5%9F_Sanat%C4%B1?f_ri=332912"}, {"id": 3039174, "name": "T\u00fcrkistan Hanl\u0131klar\u0131", "url": "https://www.academia.edu/Documents/in/T%C3%BCrkistan_Hanl%C4%B1klar%C4%B1?f_ri=332912"}, {"id": 3039175, "name": "Askeri Te\u015fkilat", "url": "https://www.academia.edu/Documents/in/Askeri_Te%C5%9Fkilat?f_ri=332912"}]}, {"id": 1150255, "title": "History's Hinge: The Battle of Ain Jalut", "created_at": "2011-12-11T17:56:44.946-08:00", "url": "https://www.academia.edu/1150255/Historys_Hinge_The_Battle_of_Ain_Jalut?f_ri=332912", "dom_id": "work_1150255", "summary": "The Battle of Ain Jalut pitted a Mamluk army against a larger Mongol army near present Ramallah. The resulting Mamluk victory shook the Mongols\u2019 belief in themselves and \u2018Ain Jalut marked the end of any concerted campaign by the Mongols in the Levant. In saving Cairo from the fate of Baghdad, the battle of \u2018Ain Jalut also sealed the doom of the relatively weaker remaining Crusader states. Mamluk Egypt rose to the pinnacle of Islamic political, military and cultural power, a position it maintained until the rise of the Ottomans some 200 years later. ", "downloadable_attachments": [{"id": 31294712, "asset_id": 1150255, "asset_type": "Work", "always_allow_download": false}], "ordered_authors": [{"id": 982727, "first_name": "David", "last_name": "Tschanz", "domain_name": "independent", "page_name": "DavidTschanz", "display_name": "David Tschanz", "profile_url": "https://independent.academia.edu/DavidTschanz?f_ri=332912", "photo": "https://0.academia-photos.com/982727/375881/455475/s65_david.tschanz.jpg"}], "research_interests": [{"id": 15800, "name": "Islamic History", "url": "https://www.academia.edu/Documents/in/Islamic_History?f_ri=332912", "nofollow": false}, {"id": 16155, "name": "Mamluk History", "url": "https://www.academia.edu/Documents/in/Mamluk_History?f_ri=332912", "nofollow": false}, {"id": 26847, "name": "Mongols", "url": "https://www.academia.edu/Documents/in/Mongols?f_ri=332912", "nofollow": false}, {"id": 332912, "name": "Islamic military history", "url": "https://www.academia.edu/Documents/in/Islamic_military_history?f_ri=332912", "nofollow": false}]}, {"id": 37367603, "title": "Mehdi Berriah, \u00ab\u00a0Un aspect de l\u2019art de la guerre de l\u2019arm\u00e9e mamelouke : la pratique de la \"fausse ouverture\" \u00e0 la bataille de \u0160aq\u1e25ab (702/1303)\u00a0\u00bb, Arabica 65, 2018, p. 431-469.", "created_at": "2018-09-09T01:50:24.542-07:00", "url": "https://www.academia.edu/37367603/Mehdi_Berriah_Un_aspect_de_l_art_de_la_guerre_de_l_arm%C3%A9e_mamelouke_la_pratique_de_la_fausse_ouverture_%C3%A0_la_bataille_de_%C5%A0aq%E1%B8%A5ab_702_1303_Arabica_65_2018_p_431_469?f_ri=332912", "dom_id": "work_37367603", "summary": null, "downloadable_attachments": [{"id": 57329099, "asset_id": 37367603, "asset_type": "Work", "always_allow_download": false}], "ordered_authors": [{"id": 10670362, "first_name": "Mehdi", "last_name": "BERRIAH", "domain_name": "independent", "page_name": "mehdiBERRIAH", "display_name": "Mehdi BERRIAH", "profile_url": "https://independent.academia.edu/mehdiBERRIAH?f_ri=332912", "photo": "https://0.academia-photos.com/10670362/15596225/35752039/s65_mehdi.berriah.jpg"}], "research_interests": [{"id": 579, "name": "Strategy (Military Science)", "url": "https://www.academia.edu/Documents/in/Strategy_Military_Science_?f_ri=332912", "nofollow": false}, {"id": 580, "name": "Tactics (Military Science)", "url": "https://www.academia.edu/Documents/in/Tactics_Military_Science_?f_ri=332912", "nofollow": false}, {"id": 6502, "name": "Mamluk Studies", "url": "https://www.academia.edu/Documents/in/Mamluk_Studies?f_ri=332912", "nofollow": false}, {"id": 16155, "name": "Mamluk History", "url": "https://www.academia.edu/Documents/in/Mamluk_History?f_ri=332912", "nofollow": false}, {"id": 25118, "name": "Medieval Islamic History", "url": "https://www.academia.edu/Documents/in/Medieval_Islamic_History?f_ri=332912"}, {"id": 67861, "name": "Medieval Military History", "url": "https://www.academia.edu/Documents/in/Medieval_Military_History?f_ri=332912"}, {"id": 263099, "name": "History and Strategic Studies", "url": "https://www.academia.edu/Documents/in/History_and_Strategic_Studies?f_ri=332912"}, {"id": 332912, "name": "Islamic military history", "url": "https://www.academia.edu/Documents/in/Islamic_military_history?f_ri=332912"}, {"id": 562475, "name": "Mamluk Military History", "url": "https://www.academia.edu/Documents/in/Mamluk_Military_History?f_ri=332912"}, {"id": 562477, "name": "Mamluk Furusiyya", "url": "https://www.academia.edu/Documents/in/Mamluk_Furusiyya?f_ri=332912"}, {"id": 894219, "name": "Islamic military", "url": "https://www.academia.edu/Documents/in/Islamic_military?f_ri=332912"}, {"id": 1265320, "name": "Military History of the Islamic World", "url": "https://www.academia.edu/Documents/in/Military_History_of_the_Islamic_World?f_ri=332912"}]}, {"id": 33017936, "title": "\u00ab\u00a0La \"grande strat\u00e9gie\" du sultanat mamelouk\u00a0dans le Proche et Moyen-Orient m\u00e9di\u00e9val (XIIIe-XVIe si\u00e8cles) \u00bb, S\u00e9minaire Jeunes Chercheurs, IRSEM/DMPA, Paris, March 22, 2017.", "created_at": "2017-05-15T00:16:03.170-07:00", "url": "https://www.academia.edu/33017936/_La_grande_strat%C3%A9gie_du_sultanat_mamelouk_dans_le_Proche_et_Moyen_Orient_m%C3%A9di%C3%A9val_XIIIe_XVIe_si%C3%A8cles_S%C3%A9minaire_Jeunes_Chercheurs_IRSEM_DMPA_Paris_March_22_2017?f_ri=332912", "dom_id": "work_33017936", "summary": null, "downloadable_attachments": [{"id": 53129811, "asset_id": 33017936, "asset_type": "Work", "always_allow_download": false}], "ordered_authors": [{"id": 10670362, "first_name": "Mehdi", "last_name": "BERRIAH", "domain_name": "independent", "page_name": "mehdiBERRIAH", "display_name": "Mehdi BERRIAH", "profile_url": "https://independent.academia.edu/mehdiBERRIAH?f_ri=332912", "photo": "https://0.academia-photos.com/10670362/15596225/35752039/s65_mehdi.berriah.jpg"}], "research_interests": [{"id": 133, "name": "Military History", "url": "https://www.academia.edu/Documents/in/Military_History?f_ri=332912", "nofollow": false}, {"id": 579, "name": "Strategy (Military Science)", "url": "https://www.academia.edu/Documents/in/Strategy_Military_Science_?f_ri=332912", "nofollow": false}, {"id": 580, "name": "Tactics (Military Science)", "url": "https://www.academia.edu/Documents/in/Tactics_Military_Science_?f_ri=332912", "nofollow": false}, {"id": 6502, "name": "Mamluk Studies", "url": "https://www.academia.edu/Documents/in/Mamluk_Studies?f_ri=332912", "nofollow": false}, {"id": 15800, "name": "Islamic History", "url": "https://www.academia.edu/Documents/in/Islamic_History?f_ri=332912"}, {"id": 16155, "name": "Mamluk History", "url": "https://www.academia.edu/Documents/in/Mamluk_History?f_ri=332912"}, {"id": 332912, "name": "Islamic military history", "url": "https://www.academia.edu/Documents/in/Islamic_military_history?f_ri=332912"}, {"id": 1265320, "name": "Military History of the Islamic World", "url": "https://www.academia.edu/Documents/in/Military_History_of_the_Islamic_World?f_ri=332912"}]}, {"id": 75141539, "title": "\"Les r\u00e9seaux de forteresses mamlukes en Syrie du Nord\", in Atlas des mondes m\u00e9di\u00e9vaux musulmans, Sylvie Denoix et H\u00e9l\u00e8ne Renel (eds.), Paris, CNRS Editions, 2022, p. 298-299", "created_at": "2022-04-01T04:07:16.768-07:00", "url": "https://www.academia.edu/75141539/_Les_r%C3%A9seaux_de_forteresses_mamlukes_en_Syrie_du_Nord_in_Atlas_des_mondes_m%C3%A9di%C3%A9vaux_musulmans_Sylvie_Denoix_et_H%C3%A9l%C3%A8ne_Renel_eds_Paris_CNRS_Editions_2022_p_298_299?f_ri=332912", "dom_id": "work_75141539", "summary": null, "downloadable_attachments": [{"id": 83029892, "asset_id": 75141539, "asset_type": "Work", "always_allow_download": false}], "ordered_authors": [{"id": 10670362, "first_name": "Mehdi", "last_name": "BERRIAH", "domain_name": "independent", "page_name": "mehdiBERRIAH", "display_name": "Mehdi BERRIAH", "profile_url": "https://independent.academia.edu/mehdiBERRIAH?f_ri=332912", "photo": "https://0.academia-photos.com/10670362/15596225/35752039/s65_mehdi.berriah.jpg"}], "research_interests": [{"id": 6502, "name": "Mamluk Studies", "url": "https://www.academia.edu/Documents/in/Mamluk_Studies?f_ri=332912", "nofollow": false}, {"id": 16155, "name": "Mamluk History", "url": "https://www.academia.edu/Documents/in/Mamluk_History?f_ri=332912", "nofollow": false}, {"id": 30702, "name": "Mamluks (Islamic History)", "url": "https://www.academia.edu/Documents/in/Mamluks_Islamic_History_?f_ri=332912", "nofollow": false}, {"id": 42271, "name": "Crusader States", "url": "https://www.academia.edu/Documents/in/Crusader_States?f_ri=332912", "nofollow": false}, {"id": 46796, "name": "Medieval Warfare", "url": "https://www.academia.edu/Documents/in/Medieval_Warfare?f_ri=332912"}, {"id": 95298, "name": "Crusaders", "url": "https://www.academia.edu/Documents/in/Crusaders?f_ri=332912"}, {"id": 332912, "name": "Islamic military history", "url": "https://www.academia.edu/Documents/in/Islamic_military_history?f_ri=332912"}, {"id": 343352, "name": "Medieval Castles and Fortresses", "url": "https://www.academia.edu/Documents/in/Medieval_Castles_and_Fortresses?f_ri=332912"}, {"id": 551809, "name": "Cilician Kingdom of Armenia", "url": "https://www.academia.edu/Documents/in/Cilician_Kingdom_of_Armenia?f_ri=332912"}, {"id": 666018, "name": "The Mamluk Sultanate", "url": "https://www.academia.edu/Documents/in/The_Mamluk_Sultanate?f_ri=332912"}, {"id": 699583, "name": "Armenian Kingdom of Cilicia", "url": "https://www.academia.edu/Documents/in/Armenian_Kingdom_of_Cilicia?f_ri=332912"}, {"id": 709694, "name": "Crusaders and Armenian Kingdom of Cilicia", "url": "https://www.academia.edu/Documents/in/Crusaders_and_Armenian_Kingdom_of_Cilicia?f_ri=332912"}, {"id": 724025, "name": "Military Strategy and Tactics", "url": "https://www.academia.edu/Documents/in/Military_Strategy_and_Tactics?f_ri=332912"}, {"id": 795458, "name": "Islamic Military Architecture", "url": "https://www.academia.edu/Documents/in/Islamic_Military_Architecture?f_ri=332912"}, {"id": 804366, "name": "Medieval Siege Warfare", "url": "https://www.academia.edu/Documents/in/Medieval_Siege_Warfare?f_ri=332912"}, {"id": 894219, "name": "Islamic military", "url": "https://www.academia.edu/Documents/in/Islamic_military?f_ri=332912"}, {"id": 1265320, "name": "Military History of the Islamic World", "url": "https://www.academia.edu/Documents/in/Military_History_of_the_Islamic_World?f_ri=332912"}, {"id": 1361140, "name": "Armenian Kingdom of Cilica", "url": "https://www.academia.edu/Documents/in/Armenian_Kingdom_of_Cilica?f_ri=332912"}, {"id": 1952102, "name": "The Fortifications of Armenian kingdom of Cilicia", "url": "https://www.academia.edu/Documents/in/The_Fortifications_of_Armenian_kingdom_of_Cilicia?f_ri=332912"}, {"id": 2517518, "name": "Bahriyya mamluks", "url": "https://www.academia.edu/Documents/in/Bahriyya_mamluks?f_ri=332912"}]}, {"id": 21764738, "title": "Black Banners from the East, Volume II: Revolt - the Social and Military aspects of the \u2018Abb\u0101sid Revolution by Prof. Moshe Sharon", "created_at": "2016-02-10T03:20:10.443-08:00", "url": "https://www.academia.edu/21764738/Black_Banners_from_the_East_Volume_II_Revolt_the_Social_and_Military_aspects_of_the_Abb%C4%81sid_Revolution_by_Prof_Moshe_Sharon?f_ri=332912", "dom_id": "work_21764738", "summary": "Black Banners from the East tells the story of the first revolution in Islam which caused not merely the change of dynasties, but the end of the formative period of Islamic civilization. It is the story of a messianic movement striving and succeeding in establishing the throne of its Caliph-Messiah. The two volumes of Black banners from the East describe the two stages of the revolution from its early Sh\u012b\u2018\u012b roots to the major military victories over the Umayyad army and the establishment of the \u2018Abb\u0101sid state. While the two volumes form a coherent study, each one of them is independent and can be read on its own.\n\nVolume II, Revolt \u2013 the social and military aspects of the \u2018Abb\u0101sid revolution, deals with the revolt itself and with it social and military aspects. It describes the rather short but decisive phase of the change that an ideological movement undergoes in order to be able to achieve its political Goal - capturing the government. The book follows step by step the emergence of the H\u0101shimiyyah-\u2018Abb\u0101siyyah from hiding into the open political and military arena, under the leadership of Ab\u016b Muslim, the character of the army it created, its social origins, its structure and the institutions which supported it. The success of the \u2018Abb\u0101s\u012b movement relied completely on the special features of this military power whose creation revolutionized, as a by-product, the whole military system in Islam.", "downloadable_attachments": [{"id": 42535092, "asset_id": 21764738, "asset_type": "Work", "always_allow_download": false}], "ordered_authors": [{"id": 25114433, "first_name": "The Max Schloessinger Memorial Foundation", "last_name": "- Jerusalem Studies in Arabic and Islam (JSAI)", "domain_name": "huji", "page_name": "TheMaxSchloessingerMemorialFoundation", "display_name": "The Max Schloessinger Memorial Foundation  - Jerusalem Studies in Arabic and Islam (JSAI)", "profile_url": "https://huji.academia.edu/TheMaxSchloessingerMemorialFoundation?f_ri=332912", "photo": "https://0.academia-photos.com/25114433/6827363/75808940/s65_the_max_schloessinger_memorial_foundation.-_jerusalem_studies_in_arabic_and_islam_jsai_.jpg"}], "research_interests": [{"id": 133, "name": "Military History", "url": "https://www.academia.edu/Documents/in/Military_History?f_ri=332912", "nofollow": false}, {"id": 6502, "name": "Mamluk Studies", "url": "https://www.academia.edu/Documents/in/Mamluk_Studies?f_ri=332912", "nofollow": false}, {"id": 11150, "name": "Islamic Studies", "url": "https://www.academia.edu/Documents/in/Islamic_Studies?f_ri=332912", "nofollow": false}, {"id": 13095, "name": "History of Caliphates", "url": "https://www.academia.edu/Documents/in/History_of_Caliphates?f_ri=332912", "nofollow": false}, {"id": 13992, "name": "Abbasid History", "url": "https://www.academia.edu/Documents/in/Abbasid_History?f_ri=332912"}, {"id": 15802, "name": "Umayyads (Islamic History)", "url": "https://www.academia.edu/Documents/in/Umayyads_Islamic_History_?f_ri=332912"}, {"id": 30047, "name": "Umayyad History", "url": "https://www.academia.edu/Documents/in/Umayyad_History?f_ri=332912"}, {"id": 34414, "name": "Abbasids (Islamic History)", "url": "https://www.academia.edu/Documents/in/Abbasids_Islamic_History_?f_ri=332912"}, {"id": 67861, "name": "Medieval Military History", "url": "https://www.academia.edu/Documents/in/Medieval_Military_History?f_ri=332912"}, {"id": 109910, "name": "Umayyad and Abbasid History", "url": "https://www.academia.edu/Documents/in/Umayyad_and_Abbasid_History?f_ri=332912"}, {"id": 177529, "name": "Umayyads", "url": "https://www.academia.edu/Documents/in/Umayyads?f_ri=332912"}, {"id": 179566, "name": "Succession to the Caliphate", "url": "https://www.academia.edu/Documents/in/Succession_to_the_Caliphate?f_ri=332912"}, {"id": 194873, "name": "History of the Islamic Middle east", "url": "https://www.academia.edu/Documents/in/History_of_the_Islamic_Middle_east?f_ri=332912"}, {"id": 253130, "name": "Turks in Abbasid armies", "url": "https://www.academia.edu/Documents/in/Turks_in_Abbasid_armies?f_ri=332912"}, {"id": 253134, "name": "Khurasanis in Abbasid armies", "url": "https://www.academia.edu/Documents/in/Khurasanis_in_Abbasid_armies?f_ri=332912"}, {"id": 332912, "name": "Islamic military history", "url": "https://www.academia.edu/Documents/in/Islamic_military_history?f_ri=332912"}, {"id": 348265, "name": "Da'wah Studies", "url": "https://www.academia.edu/Documents/in/Dawah_Studies?f_ri=332912"}, {"id": 521696, "name": "history of the middle East", "url": "https://www.academia.edu/Documents/in/history_of_the_middle_East?f_ri=332912"}, {"id": 533820, "name": "Caliphate", "url": "https://www.academia.edu/Documents/in/Caliphate?f_ri=332912"}, {"id": 720897, "name": "Umayyad Caliphate", "url": "https://www.academia.edu/Documents/in/Umayyad_Caliphate?f_ri=332912"}, {"id": 739967, "name": "Islamic governance", "url": "https://www.academia.edu/Documents/in/Islamic_governance?f_ri=332912"}, {"id": 868902, "name": "Ummayyad Caliphate", "url": "https://www.academia.edu/Documents/in/Ummayyad_Caliphate?f_ri=332912"}, {"id": 894219, "name": "Islamic military", "url": "https://www.academia.edu/Documents/in/Islamic_military?f_ri=332912"}, {"id": 1265320, "name": "Military History of the Islamic World", "url": "https://www.academia.edu/Documents/in/Military_History_of_the_Islamic_World?f_ri=332912"}]}, {"id": 6058449, "title": "\"\u02bfAyy\u0101r,\" Encyclopaedia of Islam, 3rd edition, 2014", "created_at": "2014-02-13T00:40:55.876-08:00", "url": "https://www.academia.edu/6058449/_%CA%BFAyy%C4%81r_Encyclopaedia_of_Islam_3rd_edition_2014?f_ri=332912", "dom_id": "work_6058449", "summary": null, "downloadable_attachments": [{"id": 32985222, "asset_id": 6058449, "asset_type": "Work", "always_allow_download": false}], "ordered_authors": [{"id": 344200, "first_name": "Deborah", "last_name": "Tor", "domain_name": "nd", "page_name": "DeborahTor", "display_name": "Deborah Tor", "profile_url": "https://nd.academia.edu/DeborahTor?f_ri=332912", "photo": "https://0.academia-photos.com/344200/202780/17338508/s65_deborah.tor.jpeg"}], "research_interests": [{"id": 133, "name": "Military History", "url": "https://www.academia.edu/Documents/in/Military_History?f_ri=332912", "nofollow": false}, {"id": 11152, "name": "Sufism", "url": "https://www.academia.edu/Documents/in/Sufism?f_ri=332912", "nofollow": false}, {"id": 13992, "name": "Abbasid History", "url": "https://www.academia.edu/Documents/in/Abbasid_History?f_ri=332912", "nofollow": false}, {"id": 15800, "name": "Islamic History", "url": "https://www.academia.edu/Documents/in/Islamic_History?f_ri=332912", "nofollow": false}, {"id": 25118, "name": "Medieval Islamic History", "url": "https://www.academia.edu/Documents/in/Medieval_Islamic_History?f_ri=332912"}, {"id": 42055, "name": "Early Islamic History", "url": "https://www.academia.edu/Documents/in/Early_Islamic_History?f_ri=332912"}, {"id": 332912, "name": "Islamic military history", "url": "https://www.academia.edu/Documents/in/Islamic_military_history?f_ri=332912"}, {"id": 2899814, "name": "Medieval Islamic and Turco-Iranian world, Mongol world empire", "url": "https://www.academia.edu/Documents/in/Medieval_Islamic_and_Turco-Iranian_world_Mongol_world_empire?f_ri=332912"}, {"id": 2899815, "name": "Seljuk, Mongol, post-Mongol, and Ottoman Anatolia (1200-1500)", "url": "https://www.academia.edu/Documents/in/Seljuk_Mongol_post-Mongol_and_Ottoman_Anatolia_1200-1500_?f_ri=332912"}, {"id": 2899816, "name": "Comparative empire, frontier, and political culture", "url": "https://www.academia.edu/Documents/in/Comparative_empire_frontier_and_political_culture?f_ri=332912"}, {"id": 2899817, "name": "Persian and Ottoman Turkish historical writing", "url": "https://www.academia.edu/Documents/in/Persian_and_Ottoman_Turkish_historical_writing?f_ri=332912"}]}, {"id": 49499339, "title": "\"Cyprus in the eyes of Ibn Taymiyya as the next target of Mamluk strategy in the Near East\", Seventh Conference of the School of Mamluk Studies (ONLINE) July 1-2, 2021", "created_at": "2021-07-01T12:20:21.297-07:00", "url": "https://www.academia.edu/49499339/_Cyprus_in_the_eyes_of_Ibn_Taymiyya_as_the_next_target_of_Mamluk_strategy_in_the_Near_East_Seventh_Conference_of_the_School_of_Mamluk_Studies_ONLINE_July_1_2_2021?f_ri=332912", "dom_id": "work_49499339", "summary": "During the 7th/13th \u2013 8th/14th centuries, the Mamluks fought several enemies against whom they were victorious: they managed to resist the Mongol invasions obliging the Ilkhanids to be at the initiative of a peace proposal; to expel the Franks from Syria and conquer their territories; to weaken the kingdom of Armenia before conquering it throughout the 8th/14th century.\nWhat about Cyprus? Except for the expedition that Baybars launched against the island in shaww\u0101l 669/May 1271, an expedition that failed, and al-Ashraf Khalil\u2019s declaration of wanting to conquer it, Cyprus did not constitute, according to the sources, a significant objective of the Mamluk Sultanate during the second half of the 7th/13th century. However, at the beginning of the 8th/14th century, and for obvious reasons of international politics, Cyprus attracted more attention of the Mamluks, as the examination of the sources confirms, in particular, the writings of Ibn Taymiyya.\u00a0\nIf the latter, in his\u00a0Ris\u0101la al-qubru\u1e63iyya, adopts a moderate tone, which is different from the one that usually characterises it in his other writings, it is to obtain the good treatment of the Muslim prisoners present in Cyprus and the opening of negotiations for their release. Nevertheless, the analysis of several passages of the text brings out indirect discourses that make it possible to identify, with other sources, Ibn Taymiyya\u2019s perception of the Kingdom of Cyprus: a cross-power that represented a potential threat and against which the Sultanate must lead the jihad.\nWhen he mentions the defeat of the Mongols and their Armenian allies, Ibn Taymiyya denounces, implicitly, the role of Cyprus and its participation in the war against the Sultanate, and the failure of plans for joint attacks between the Crusader forces crossed, of which Cyprus is a part and the Mongols. In addition, the praise of the military force of the Mamluk Sultanate by Ibn Taymiyya, who goes so far as to extol the Assassins\u2019 ability to reach their target (despite his utter opposition to their belief that he considers as heretic), can be understood as a warning to the Cypriot authorities against potential retaliation by the Mamluks.\nFinally, the memory of the Cyprus Muslim period reflects a certain nostalgia of Ibn Taymiyya and, consequently, his wish for a \u2018reconquest\u2019 by the Mamluks.\nBased on Arabic sources, this submission proposes to shed light on Ibn Taymiyya\u2019s perception of Cyprus as the next target of Mamluk strategy; on the one hand, by analysing his discourse and confronting it on the other hand to other sources.", "downloadable_attachments": [{"id": 67837763, "asset_id": 49499339, "asset_type": "Work", "always_allow_download": false}], "ordered_authors": [{"id": 10670362, "first_name": "Mehdi", "last_name": "BERRIAH", "domain_name": "independent", "page_name": "mehdiBERRIAH", "display_name": "Mehdi BERRIAH", "profile_url": "https://independent.academia.edu/mehdiBERRIAH?f_ri=332912", "photo": "https://0.academia-photos.com/10670362/15596225/35752039/s65_mehdi.berriah.jpg"}], "research_interests": [{"id": 4054, "name": "Cyprus Studies", "url": "https://www.academia.edu/Documents/in/Cyprus_Studies?f_ri=332912", "nofollow": false}, {"id": 6502, "name": "Mamluk Studies", "url": "https://www.academia.edu/Documents/in/Mamluk_Studies?f_ri=332912", "nofollow": false}, {"id": 14363, "name": "Cyprus conflict", "url": "https://www.academia.edu/Documents/in/Cyprus_conflict?f_ri=332912", "nofollow": false}, {"id": 16155, "name": "Mamluk History", "url": "https://www.academia.edu/Documents/in/Mamluk_History?f_ri=332912", "nofollow": false}, {"id": 25118, "name": "Medieval Islamic History", "url": "https://www.academia.edu/Documents/in/Medieval_Islamic_History?f_ri=332912"}, {"id": 30702, "name": "Mamluks (Islamic History)", "url": "https://www.academia.edu/Documents/in/Mamluks_Islamic_History_?f_ri=332912"}, {"id": 46796, "name": "Medieval Warfare", "url": "https://www.academia.edu/Documents/in/Medieval_Warfare?f_ri=332912"}, {"id": 51858, "name": "Jihad", "url": "https://www.academia.edu/Documents/in/Jihad?f_ri=332912"}, {"id": 80338, "name": "Ibn Taymiyya", "url": "https://www.academia.edu/Documents/in/Ibn_Taymiyya?f_ri=332912"}, {"id": 86109, "name": "Cyprus and the East Mediterranean", "url": "https://www.academia.edu/Documents/in/Cyprus_and_the_East_Mediterranean?f_ri=332912"}, {"id": 216637, "name": "Medieval Cyprus", "url": "https://www.academia.edu/Documents/in/Medieval_Cyprus?f_ri=332912"}, {"id": 332912, "name": "Islamic military history", "url": "https://www.academia.edu/Documents/in/Islamic_military_history?f_ri=332912"}, {"id": 427387, "name": "Global Jihad", "url": "https://www.academia.edu/Documents/in/Global_Jihad?f_ri=332912"}, {"id": 448365, "name": "Mongols and Mamluks", "url": "https://www.academia.edu/Documents/in/Mongols_and_Mamluks?f_ri=332912"}, {"id": 580268, "name": "ibn Taymiyyah", "url": "https://www.academia.edu/Documents/in/ibn_Taymiyyah?f_ri=332912"}, {"id": 1265320, "name": "Military History of the Islamic World", "url": "https://www.academia.edu/Documents/in/Military_History_of_the_Islamic_World?f_ri=332912"}, {"id": 2517518, "name": "Bahriyya mamluks", "url": "https://www.academia.edu/Documents/in/Bahriyya_mamluks?f_ri=332912"}]}, {"id": 8812594, "title": "Un arciere saraceno in un manoscritto del XIII secolo", "created_at": "2014-10-16T05:07:49.493-07:00", "url": "https://www.academia.edu/8812594/Un_arciere_saraceno_in_un_manoscritto_del_XIII_secolo?f_ri=332912", "dom_id": "work_8812594", "summary": null, "downloadable_attachments": [{"id": 35157970, "asset_id": 8812594, "asset_type": "Work", "always_allow_download": false}], "ordered_authors": [{"id": 7855256, "first_name": "Alessandro", "last_name": "De Troia", "domain_name": "unibo", "page_name": "AlessandroDeTroia", "display_name": "Alessandro De Troia", "profile_url": "https://unibo.academia.edu/AlessandroDeTroia?f_ri=332912", "photo": "https://0.academia-photos.com/7855256/3242789/35023827/s65_alessandro.de_troia.jpg"}, {"id": 7913774, "first_name": "Alessandro", "last_name": "Strinati", "domain_name": "independent", "page_name": "AlessandroStrinati", "display_name": "Alessandro Strinati", "profile_url": "https://independent.academia.edu/AlessandroStrinati?f_ri=332912", "photo": "https://0.academia-photos.com/7913774/2797734/3262425/s65_alessandro.strinati.jpg"}], "research_interests": [{"id": 128, "name": "History", "url": "https://www.academia.edu/Documents/in/History?f_ri=332912", "nofollow": false}, {"id": 133, "name": "Military History", "url": "https://www.academia.edu/Documents/in/Military_History?f_ri=332912", "nofollow": false}, {"id": 1446, "name": "Medieval History", "url": "https://www.academia.edu/Documents/in/Medieval_History?f_ri=332912", "nofollow": false}, {"id": 26891, "name": "Manuscripts (Medieval Studies)", "url": "https://www.academia.edu/Documents/in/Manuscripts_Medieval_Studies_?f_ri=332912", "nofollow": false}, {"id": 38565, "name": "Lucera - Muslim City in Medieval Apulia", "url": "https://www.academia.edu/Documents/in/Lucera_-_Muslim_City_in_Medieval_Apulia?f_ri=332912"}, {"id": 67861, "name": "Medieval Military History", "url": "https://www.academia.edu/Documents/in/Medieval_Military_History?f_ri=332912"}, {"id": 132665, "name": "Saracens", "url": "https://www.academia.edu/Documents/in/Saracens?f_ri=332912"}, {"id": 332912, "name": "Islamic military history", "url": "https://www.academia.edu/Documents/in/Islamic_military_history?f_ri=332912"}, {"id": 374793, "name": "Emperor Frederick II", "url": "https://www.academia.edu/Documents/in/Emperor_Frederick_II?f_ri=332912"}, {"id": 650094, "name": "Storia Militare", "url": "https://www.academia.edu/Documents/in/Storia_Militare?f_ri=332912"}, {"id": 867393, "name": "Charles of Anjou, King of Sicily", "url": "https://www.academia.edu/Documents/in/Charles_of_Anjou_King_of_Sicily?f_ri=332912"}, {"id": 873483, "name": "Luceria", "url": "https://www.academia.edu/Documents/in/Luceria?f_ri=332912"}, {"id": 992483, "name": "Saraceni", "url": "https://www.academia.edu/Documents/in/Saraceni?f_ri=332912"}, {"id": 1159408, "name": "Carlo I d'Angi\u00f2", "url": "https://www.academia.edu/Documents/in/Carlo_I_dAngio?f_ri=332912"}, {"id": 1199645, "name": "Manfredi Re Di Sicilia", "url": "https://www.academia.edu/Documents/in/Manfredi_Re_Di_Sicilia?f_ri=332912"}, {"id": 1287958, "name": "Storia Militare Medievale", "url": "https://www.academia.edu/Documents/in/Storia_Militare_Medievale?f_ri=332912"}, {"id": 1349663, "name": "Saracens In Medieval Literature", "url": "https://www.academia.edu/Documents/in/Saracens_In_Medieval_Literature?f_ri=332912"}]}, {"id": 53752830, "title": "Programme workshop Jihad in Medieval Islam: Texts, Theories and Practices (7th-14th), The French Institute for Oriental Archaeology (Ifao), Cairo, October 11, 2021", "created_at": "2021-09-28T10:21:33.700-07:00", "url": "https://www.academia.edu/53752830/Programme_workshop_Jihad_in_Medieval_Islam_Texts_Theories_and_Practices_7th_14th_The_French_Institute_for_Oriental_Archaeology_Ifao_Cairo_October_11_2021?f_ri=332912", "dom_id": "work_53752830", "summary": null, "downloadable_attachments": [{"id": 70447631, "asset_id": 53752830, "asset_type": "Work", "always_allow_download": false}], "ordered_authors": [{"id": 10670362, "first_name": "Mehdi", "last_name": "BERRIAH", "domain_name": "independent", "page_name": "mehdiBERRIAH", "display_name": "Mehdi BERRIAH", "profile_url": "https://independent.academia.edu/mehdiBERRIAH?f_ri=332912", "photo": "https://0.academia-photos.com/10670362/15596225/35752039/s65_mehdi.berriah.jpg"}], "research_interests": [{"id": 51858, "name": "Jihad", "url": "https://www.academia.edu/Documents/in/Jihad?f_ri=332912", "nofollow": false}, {"id": 89401, "name": "Jihad, War, and Peace in Islam", "url": "https://www.academia.edu/Documents/in/Jihad_War_and_Peace_in_Islam?f_ri=332912", "nofollow": false}, {"id": 167288, "name": "jihad, war and peace, rules of warfare in Islam", "url": "https://www.academia.edu/Documents/in/jihad_war_and_peace_rules_of_warfare_in_Islam?f_ri=332912", "nofollow": false}, {"id": 332912, "name": "Islamic military history", "url": "https://www.academia.edu/Documents/in/Islamic_military_history?f_ri=332912", "nofollow": false}, {"id": 516537, "name": "Jihad, Qur'an, Just War", "url": "https://www.academia.edu/Documents/in/Jihad_Quran_Just_War?f_ri=332912"}, {"id": 894221, "name": "Islamic Jihad", "url": "https://www.academia.edu/Documents/in/Islamic_Jihad?f_ri=332912"}, {"id": 1265320, "name": "Military History of the Islamic World", "url": "https://www.academia.edu/Documents/in/Military_History_of_the_Islamic_World?f_ri=332912"}, {"id": 1666631, "name": "Jihad and Just War", "url": "https://www.academia.edu/Documents/in/Jihad_and_Just_War?f_ri=332912"}, {"id": 1724153, "name": "History of Islamic jihad", "url": "https://www.academia.edu/Documents/in/History_of_Islamic_jihad?f_ri=332912"}, {"id": 1780324, "name": "Jihad and Political Islam", "url": "https://www.academia.edu/Documents/in/Jihad_and_Political_Islam?f_ri=332912"}]}, {"id": 49421124, "title": "\"Eychenne Mathieu, Pradines St\u00e9phane and Zouache Abb\u00e8s (dir.), Guerre et paix dans le Proche-Orient m\u00e9di\u00e9val (xe-xve si\u00e8cle)\", Revue des mondes musulmans et de la M\u00e9diterran\u00e9e [online], 149 | June 2021", "created_at": "2021-06-27T06:42:20.070-07:00", "url": "https://www.academia.edu/49421124/_Eychenne_Mathieu_Pradines_St%C3%A9phane_and_Zouache_Abb%C3%A8s_dir_Guerre_et_paix_dans_le_Proche_Orient_m%C3%A9di%C3%A9val_xe_xve_si%C3%A8cle_Revue_des_mondes_musulmans_et_de_la_M%C3%A9diterran%C3%A9e_online_149_June_2021?f_ri=332912", "dom_id": "work_49421124", "summary": "https://journals.openedition.org/remmm/15003", "downloadable_attachments": [{"id": 67776153, "asset_id": 49421124, "asset_type": "Work", "always_allow_download": false}], "ordered_authors": [{"id": 10670362, "first_name": "Mehdi", "last_name": "BERRIAH", "domain_name": "independent", "page_name": "mehdiBERRIAH", "display_name": "Mehdi BERRIAH", "profile_url": "https://independent.academia.edu/mehdiBERRIAH?f_ri=332912", "photo": "https://0.academia-photos.com/10670362/15596225/35752039/s65_mehdi.berriah.jpg"}], "research_interests": [{"id": 51858, "name": "Jihad", "url": "https://www.academia.edu/Documents/in/Jihad?f_ri=332912", "nofollow": false}, {"id": 67861, "name": "Medieval Military History", "url": "https://www.academia.edu/Documents/in/Medieval_Military_History?f_ri=332912", "nofollow": false}, {"id": 89401, "name": "Jihad, War, and Peace in Islam", "url": "https://www.academia.edu/Documents/in/Jihad_War_and_Peace_in_Islam?f_ri=332912", "nofollow": false}, {"id": 167288, "name": "jihad, war and peace, rules of warfare in Islam", "url": "https://www.academia.edu/Documents/in/jihad_war_and_peace_rules_of_warfare_in_Islam?f_ri=332912", "nofollow": false}, {"id": 194873, "name": "History of the Islamic Middle east", "url": "https://www.academia.edu/Documents/in/History_of_the_Islamic_Middle_east?f_ri=332912"}, {"id": 332912, "name": "Islamic military history", "url": "https://www.academia.edu/Documents/in/Islamic_military_history?f_ri=332912"}, {"id": 521696, "name": "history of the middle East", "url": "https://www.academia.edu/Documents/in/history_of_the_middle_East?f_ri=332912"}, {"id": 795458, "name": "Islamic Military Architecture", "url": "https://www.academia.edu/Documents/in/Islamic_Military_Architecture?f_ri=332912"}, {"id": 1265320, "name": "Military History of the Islamic World", "url": "https://www.academia.edu/Documents/in/Military_History_of_the_Islamic_World?f_ri=332912"}, {"id": 1748131, "name": "Military History of the Middle Ages", "url": "https://www.academia.edu/Documents/in/Military_History_of_the_Middle_Ages?f_ri=332912"}]}, {"id": 54370651, "title": "\"The Issue of Financing Jih\u0101d in Islamic Law: Three Case Studies from the Maml\u016bk Period\", ShariaSOURCE - Program of Islamic Law - Harvard School of Law, September 2021", "created_at": "2021-09-30T09:43:11.664-07:00", "url": "https://www.academia.edu/54370651/_The_Issue_of_Financing_Jih%C4%81d_in_Islamic_Law_Three_Case_Studies_from_the_Maml%C5%ABk_Period_ShariaSOURCE_Program_of_Islamic_Law_Harvard_School_of_Law_September_2021?f_ri=332912", "dom_id": "work_54370651", "summary": "https://islamiclaw.blog/tag/mehdi-berriah/", "downloadable_attachments": [{"id": 70791594, "asset_id": 54370651, "asset_type": "Work", "always_allow_download": false}], "ordered_authors": [{"id": 10670362, "first_name": "Mehdi", "last_name": "BERRIAH", "domain_name": "independent", "page_name": "mehdiBERRIAH", "display_name": "Mehdi BERRIAH", "profile_url": "https://independent.academia.edu/mehdiBERRIAH?f_ri=332912", "photo": "https://0.academia-photos.com/10670362/15596225/35752039/s65_mehdi.berriah.jpg"}], "research_interests": [{"id": 540, "name": "Islamic Law", "url": "https://www.academia.edu/Documents/in/Islamic_Law?f_ri=332912", "nofollow": false}, {"id": 16155, "name": "Mamluk History", "url": "https://www.academia.edu/Documents/in/Mamluk_History?f_ri=332912", "nofollow": false}, {"id": 30702, "name": "Mamluks (Islamic History)", "url": "https://www.academia.edu/Documents/in/Mamluks_Islamic_History_?f_ri=332912", "nofollow": false}, {"id": 51858, "name": "Jihad", "url": "https://www.academia.edu/Documents/in/Jihad?f_ri=332912", "nofollow": false}, {"id": 80338, "name": "Ibn Taymiyya", "url": "https://www.academia.edu/Documents/in/Ibn_Taymiyya?f_ri=332912"}, {"id": 97959, "name": "Law and Jurisprudence", "url": "https://www.academia.edu/Documents/in/Law_and_Jurisprudence?f_ri=332912"}, {"id": 125423, "name": "Jihadism", "url": "https://www.academia.edu/Documents/in/Jihadism?f_ri=332912"}, {"id": 127680, "name": "Fatwa and Islamic Shariah Law", "url": "https://www.academia.edu/Documents/in/Fatwa_and_Islamic_Shariah_Law?f_ri=332912"}, {"id": 167288, "name": "jihad, war and peace, rules of warfare in Islam", "url": "https://www.academia.edu/Documents/in/jihad_war_and_peace_rules_of_warfare_in_Islam?f_ri=332912"}, {"id": 299426, "name": "The Shafi'i school of law", "url": "https://www.academia.edu/Documents/in/The_Shafii_school_of_law?f_ri=332912"}, {"id": 332912, "name": "Islamic military history", "url": "https://www.academia.edu/Documents/in/Islamic_military_history?f_ri=332912"}, {"id": 580268, "name": "ibn Taymiyyah", "url": "https://www.academia.edu/Documents/in/ibn_Taymiyyah?f_ri=332912"}, {"id": 894219, "name": "Islamic military", "url": "https://www.academia.edu/Documents/in/Islamic_military?f_ri=332912"}, {"id": 1003149, "name": "Oulemas", "url": "https://www.academia.edu/Documents/in/Oulemas?f_ri=332912"}, {"id": 1265320, "name": "Military History of the Islamic World", "url": "https://www.academia.edu/Documents/in/Military_History_of_the_Islamic_World?f_ri=332912"}, {"id": 1569019, "name": "Muslim Scholars", "url": "https://www.academia.edu/Documents/in/Muslim_Scholars?f_ri=332912"}, {"id": 1666631, "name": "Jihad and Just War", "url": "https://www.academia.edu/Documents/in/Jihad_and_Just_War?f_ri=332912"}, {"id": 3048605, "name": "the Malik\u00ee School of law", "url": "https://www.academia.edu/Documents/in/the_Malik%C3%AE_School_of_law?f_ri=332912"}, {"id": 3074983, "name": "Ibn Taymiyyah's", "url": "https://www.academia.edu/Documents/in/Ibn_Taymiyyahs?f_ri=332912"}, {"id": 3851535, "name": "The Hanafid School of Law", "url": "https://www.academia.edu/Documents/in/The_Hanafid_School_of_Law?f_ri=332912"}]}, {"id": 49971860, "title": "Call for papers \"Jihad in Medieval Islam. Texts, Theories and Practices (7th-14th c.)\", The French Institute for Oriental Archaeology (Ifao), Cairo, 11 October 2021", "created_at": "2021-07-16T00:42:28.127-07:00", "url": "https://www.academia.edu/49971860/Call_for_papers_Jihad_in_Medieval_Islam_Texts_Theories_and_Practices_7th_14th_c_The_French_Institute_for_Oriental_Archaeology_Ifao_Cairo_11_October_2021?f_ri=332912", "dom_id": "work_49971860", "summary": null, "downloadable_attachments": [{"id": 68130352, "asset_id": 49971860, "asset_type": "Work", "always_allow_download": false}], "ordered_authors": [{"id": 10670362, "first_name": "Mehdi", "last_name": "BERRIAH", "domain_name": "independent", "page_name": "mehdiBERRIAH", "display_name": "Mehdi BERRIAH", "profile_url": "https://independent.academia.edu/mehdiBERRIAH?f_ri=332912", "photo": "https://0.academia-photos.com/10670362/15596225/35752039/s65_mehdi.berriah.jpg"}], "research_interests": [{"id": 540, "name": "Islamic Law", "url": "https://www.academia.edu/Documents/in/Islamic_Law?f_ri=332912", "nofollow": false}, {"id": 19609, "name": "History of Military Technology", "url": "https://www.academia.edu/Documents/in/History_of_Military_Technology?f_ri=332912", "nofollow": false}, {"id": 25118, "name": "Medieval Islamic History", "url": "https://www.academia.edu/Documents/in/Medieval_Islamic_History?f_ri=332912", "nofollow": false}, {"id": 44426, "name": "Military Studies", "url": "https://www.academia.edu/Documents/in/Military_Studies?f_ri=332912", "nofollow": false}, {"id": 51858, "name": "Jihad", "url": "https://www.academia.edu/Documents/in/Jihad?f_ri=332912"}, {"id": 67861, "name": "Medieval Military History", "url": "https://www.academia.edu/Documents/in/Medieval_Military_History?f_ri=332912"}, {"id": 89401, "name": "Jihad, War, and Peace in Islam", "url": "https://www.academia.edu/Documents/in/Jihad_War_and_Peace_in_Islam?f_ri=332912"}, {"id": 95176, "name": "JIhad, War and Peace in Islam", "url": "https://www.academia.edu/Documents/in/JIhad_War_and_Peace_in_Islam-1?f_ri=332912"}, {"id": 167288, "name": "jihad, war and peace, rules of warfare in Islam", "url": "https://www.academia.edu/Documents/in/jihad_war_and_peace_rules_of_warfare_in_Islam?f_ri=332912"}, {"id": 179944, "name": "rules of warfare in Islam", "url": "https://www.academia.edu/Documents/in/rules_of_warfare_in_Islam?f_ri=332912"}, {"id": 332912, "name": "Islamic military history", "url": "https://www.academia.edu/Documents/in/Islamic_military_history?f_ri=332912"}, {"id": 516537, "name": "Jihad, Qur'an, Just War", "url": "https://www.academia.edu/Documents/in/Jihad_Quran_Just_War?f_ri=332912"}, {"id": 894219, "name": "Islamic military", "url": "https://www.academia.edu/Documents/in/Islamic_military?f_ri=332912"}, {"id": 894220, "name": "Islamic warfare", "url": "https://www.academia.edu/Documents/in/Islamic_warfare?f_ri=332912"}, {"id": 1003149, "name": "Oulemas", "url": "https://www.academia.edu/Documents/in/Oulemas?f_ri=332912"}, {"id": 1203924, "name": "Islamic Law of War and Peace", "url": "https://www.academia.edu/Documents/in/Islamic_Law_of_War_and_Peace?f_ri=332912"}, {"id": 1265320, "name": "Military History of the Islamic World", "url": "https://www.academia.edu/Documents/in/Military_History_of_the_Islamic_World?f_ri=332912"}, {"id": 1410499, "name": "Military History and Strategic Studies", "url": "https://www.academia.edu/Documents/in/Military_History_and_Strategic_Studies?f_ri=332912"}, {"id": 1666631, "name": "Jihad and Just War", "url": "https://www.academia.edu/Documents/in/Jihad_and_Just_War?f_ri=332912"}, {"id": 1805387, "name": "Islam and violence", "url": "https://www.academia.edu/Documents/in/Islam_and_violence?f_ri=332912"}]}, {"id": 37367573, "title": "Workshop, \u00ab\u00a0\u01e6ih\u0101d et fitna : penser et concevoir la guerre dans le Ma\u0161riq m\u00e9di\u00e9val (XIe-XVIe si\u00e8cles)\u00bb, UMR 8167 Orient et M\u00e9diterran\u00e9e, CEFAS, Horn East, University of Paris Panth\u00e9on-La Sorbonne, Paris, January 24, 2018.", "created_at": "2018-09-09T01:34:54.952-07:00", "url": "https://www.academia.edu/37367573/Workshop_%C7%A6ih%C4%81d_et_fitna_penser_et_concevoir_la_guerre_dans_le_Ma%C5%A1riq_m%C3%A9di%C3%A9val_XIe_XVIe_si%C3%A8cles_UMR_8167_Orient_et_M%C3%A9diterran%C3%A9e_CEFAS_Horn_East_University_of_Paris_Panth%C3%A9on_La_Sorbonne_Paris_January_24_2018?f_ri=332912", "dom_id": "work_37367573", "summary": null, "downloadable_attachments": [{"id": 57329087, "asset_id": 37367573, "asset_type": "Work", "always_allow_download": false}], "ordered_authors": [{"id": 10670362, "first_name": "Mehdi", "last_name": "BERRIAH", "domain_name": "independent", "page_name": "mehdiBERRIAH", "display_name": "Mehdi BERRIAH", "profile_url": "https://independent.academia.edu/mehdiBERRIAH?f_ri=332912", "photo": "https://0.academia-photos.com/10670362/15596225/35752039/s65_mehdi.berriah.jpg"}], "research_interests": [{"id": 6502, "name": "Mamluk Studies", "url": "https://www.academia.edu/Documents/in/Mamluk_Studies?f_ri=332912", "nofollow": false}, {"id": 11150, "name": "Islamic Studies", "url": "https://www.academia.edu/Documents/in/Islamic_Studies?f_ri=332912", "nofollow": false}, {"id": 16155, "name": "Mamluk History", "url": "https://www.academia.edu/Documents/in/Mamluk_History?f_ri=332912", "nofollow": false}, {"id": 25118, "name": "Medieval Islamic History", "url": "https://www.academia.edu/Documents/in/Medieval_Islamic_History?f_ri=332912", "nofollow": false}, {"id": 51858, "name": "Jihad", "url": "https://www.academia.edu/Documents/in/Jihad?f_ri=332912"}, {"id": 95178, "name": "Islamic Classical Jurisprudence (fiqh)", "url": "https://www.academia.edu/Documents/in/Islamic_Classical_Jurisprudence_fiqh_?f_ri=332912"}, {"id": 332912, "name": "Islamic military history", "url": "https://www.academia.edu/Documents/in/Islamic_military_history?f_ri=332912"}, {"id": 469642, "name": "Jihadism and Radical Islamism", "url": "https://www.academia.edu/Documents/in/Jihadism_and_Radical_Islamism?f_ri=332912"}]}]